<?xml version="1.0" standalone="yes" ?>
<DBMODEL Version="4.0">
<SETTINGS>
<GLOBALSETTINGS ModelName="trabalho" IDModel="0" IDVersion="0" VersionStr="1.0.0.0" Comments="" UseVersionHistroy="1" AutoIncVersion="1" DatabaseType="MySQL" ZoomFac="42.19" XPos="0" YPos="0" DefaultDataType="5" DefaultTablePrefix="0" DefSaveDBConn="" DefSyncDBConn="" DefQueryDBConn="" Printer="Enviar para o OneNote 2010" HPageCount="4.0" PageAspectRatio="1.414162639209918" PageOrientation="1" PageFormat="A4 (210x297 mm, 8.26x11.7 inches)" SelectedPages="0;1;2;4;5" UsePositionGrid="0" PositionGridX="20" PositionGridY="20" TableNameInRefs="0" DefaultTableType="0" ActivateRefDefForNewRelations="1" FKPrefix="" FKPostfix="" CreateFKRefDefIndex="1" DBQuoteCharacter="`" CreateSQLforLinkedObjects="0" DefModelFont="Tahoma" CanvasWidth="4096" CanvasHeight="2842" />
<DATATYPEGROUPS>
<DATATYPEGROUP Name="Numeric Types" Icon="1" />
<DATATYPEGROUP Name="Date and Time Types" Icon="2" />
<DATATYPEGROUP Name="String Types" Icon="3" />
<DATATYPEGROUP Name="Blob and Text Types" Icon="4" />
<DATATYPEGROUP Name="User defined Types" Icon="5" />
<DATATYPEGROUP Name="Geographic Types" Icon="6" />
</DATATYPEGROUPS>
<DATATYPES>
<DATATYPE ID="1" IDGroup="0" TypeName="TINYINT" Description="A very small integer. The signed range is -128 to 127. The unsigned range is 0 to 255." ParamCount="1" OptionCount="2" ParamRequired="0" EditParamsAsString="0" SynonymGroup="0" PhysicalMapping="0" PhysicalTypeName="" >
<PARAMS>
<PARAM Name="length" />
</PARAMS>
<OPTIONS>
<OPTION Name="UNSIGNED" Default="1" />
<OPTION Name="ZEROFILL" Default="0" />
</OPTIONS>
</DATATYPE>
<DATATYPE ID="2" IDGroup="0" TypeName="SMALLINT" Description="A small integer. The signed range is -32768 to 32767. The unsigned range is 0 to 65535." ParamCount="1" OptionCount="2" ParamRequired="0" EditParamsAsString="0" SynonymGroup="0" PhysicalMapping="0" PhysicalTypeName="" >
<PARAMS>
<PARAM Name="length" />
</PARAMS>
<OPTIONS>
<OPTION Name="UNSIGNED" Default="1" />
<OPTION Name="ZEROFILL" Default="0" />
</OPTIONS>
</DATATYPE>
<DATATYPE ID="3" IDGroup="0" TypeName="MEDIUMINT" Description="A medium-size integer. The signed range is -8388608 to 8388607. The unsigned range is 0 to 16777215." ParamCount="1" OptionCount="2" ParamRequired="0" EditParamsAsString="0" SynonymGroup="0" PhysicalMapping="0" PhysicalTypeName="" >
<PARAMS>
<PARAM Name="length" />
</PARAMS>
<OPTIONS>
<OPTION Name="UNSIGNED" Default="1" />
<OPTION Name="ZEROFILL" Default="0" />
</OPTIONS>
</DATATYPE>
<DATATYPE ID="4" IDGroup="0" TypeName="INT" Description="A normal-size integer. The signed range is -2147483648 to 2147483647. The unsigned range is 0 to 4294967295." ParamCount="1" OptionCount="2" ParamRequired="0" EditParamsAsString="0" SynonymGroup="1" PhysicalMapping="0" PhysicalTypeName="" >
<PARAMS>
<PARAM Name="length" />
</PARAMS>
<OPTIONS>
<OPTION Name="UNSIGNED" Default="0" />
<OPTION Name="ZEROFILL" Default="0" />
</OPTIONS>
</DATATYPE>
<DATATYPE ID="5" IDGroup="0" TypeName="INTEGER" Description="A normal-size integer. The signed range is -2147483648 to 2147483647. The unsigned range is 0 to 4294967295." ParamCount="1" OptionCount="2" ParamRequired="0" EditParamsAsString="0" SynonymGroup="1" PhysicalMapping="0" PhysicalTypeName="" >
<PARAMS>
<PARAM Name="length" />
</PARAMS>
<OPTIONS>
<OPTION Name="UNSIGNED" Default="1" />
<OPTION Name="ZEROFILL" Default="0" />
</OPTIONS>
</DATATYPE>
<DATATYPE ID="6" IDGroup="0" TypeName="BIGINT" Description="A large integer. The signed range is -9223372036854775808 to 9223372036854775807. The unsigned range is 0 to 18446744073709551615." ParamCount="1" OptionCount="2" ParamRequired="0" EditParamsAsString="0" SynonymGroup="0" PhysicalMapping="0" PhysicalTypeName="" >
<PARAMS>
<PARAM Name="length" />
</PARAMS>
<OPTIONS>
<OPTION Name="UNSIGNED" Default="0" />
<OPTION Name="ZEROFILL" Default="0" />
</OPTIONS>
</DATATYPE>
<DATATYPE ID="7" IDGroup="0" TypeName="FLOAT" Description="A small (single-precision) floating-point number. Cannot be unsigned. Allowable values are -3.402823466E+38 to -1.175494351E-38, 0, and 1.175494351E-38 to 3.402823466E+38." ParamCount="1" OptionCount="1" ParamRequired="1" EditParamsAsString="0" SynonymGroup="0" PhysicalMapping="0" PhysicalTypeName="" >
<PARAMS>
<PARAM Name="precision" />
</PARAMS>
<OPTIONS>
<OPTION Name="ZEROFILL" Default="0" />
</OPTIONS>
</DATATYPE>
<DATATYPE ID="8" IDGroup="0" TypeName="FLOAT" Description="A small (single-precision) floating-point number. Cannot be unsigned. Allowable values are -3.402823466E+38 to -1.175494351E-38, 0, and 1.175494351E-38 to 3.402823466E+38." ParamCount="2" OptionCount="1" ParamRequired="0" EditParamsAsString="0" SynonymGroup="0" PhysicalMapping="0" PhysicalTypeName="" >
<PARAMS>
<PARAM Name="length" />
<PARAM Name="decimals" />
</PARAMS>
<OPTIONS>
<OPTION Name="ZEROFILL" Default="0" />
</OPTIONS>
</DATATYPE>
<DATATYPE ID="9" IDGroup="0" TypeName="DOUBLE" Description="A normal-size (double-precision) floating-point number. Cannot be unsigned. Allowable values are -1.7976931348623157E+308 to -2.2250738585072014E-308, 0, and 2.2250738585072014E-308 to 1.7976931348623157E+308." ParamCount="2" OptionCount="1" ParamRequired="0" EditParamsAsString="0" SynonymGroup="2" PhysicalMapping="0" PhysicalTypeName="" >
<PARAMS>
<PARAM Name="length" />
<PARAM Name="decimals" />
</PARAMS>
<OPTIONS>
<OPTION Name="ZEROFILL" Default="0" />
</OPTIONS>
</DATATYPE>
<DATATYPE ID="10" IDGroup="0" TypeName="DOUBLE PRECISION" Description="This is a synonym for DOUBLE." ParamCount="2" OptionCount="1" ParamRequired="0" EditParamsAsString="0" SynonymGroup="2" PhysicalMapping="0" PhysicalTypeName="" >
<PARAMS>
<PARAM Name="length" />
<PARAM Name="decimals" />
</PARAMS>
<OPTIONS>
<OPTION Name="ZEROFILL" Default="0" />
</OPTIONS>
</DATATYPE>
<DATATYPE ID="11" IDGroup="0" TypeName="REAL" Description="This is a synonym for DOUBLE." ParamCount="2" OptionCount="1" ParamRequired="0" EditParamsAsString="0" SynonymGroup="2" PhysicalMapping="0" PhysicalTypeName="" >
<PARAMS>
<PARAM Name="length" />
<PARAM Name="decimals" />
</PARAMS>
<OPTIONS>
<OPTION Name="ZEROFILL" Default="0" />
</OPTIONS>
</DATATYPE>
<DATATYPE ID="12" IDGroup="0" TypeName="DECIMAL" Description="An unpacked floating-point number. Cannot be unsigned. Behaves like a CHAR column." ParamCount="2" OptionCount="1" ParamRequired="0" EditParamsAsString="0" SynonymGroup="3" PhysicalMapping="0" PhysicalTypeName="" >
<PARAMS>
<PARAM Name="length" />
<PARAM Name="decimals" />
</PARAMS>
<OPTIONS>
<OPTION Name="ZEROFILL" Default="0" />
</OPTIONS>
</DATATYPE>
<DATATYPE ID="13" IDGroup="0" TypeName="NUMERIC" Description="This is a synonym for DECIMAL." ParamCount="2" OptionCount="1" ParamRequired="1" EditParamsAsString="0" SynonymGroup="3" PhysicalMapping="0" PhysicalTypeName="" >
<PARAMS>
<PARAM Name="length" />
<PARAM Name="decimals" />
</PARAMS>
<OPTIONS>
<OPTION Name="ZEROFILL" Default="0" />
</OPTIONS>
</DATATYPE>
<DATATYPE ID="14" IDGroup="1" TypeName="DATE" Description="A date. The supported range is \a1000-01-01\a to \a9999-12-31\a." ParamCount="0" OptionCount="0" ParamRequired="0" EditParamsAsString="0" SynonymGroup="0" PhysicalMapping="0" PhysicalTypeName="" >
</DATATYPE>
<DATATYPE ID="15" IDGroup="1" TypeName="DATETIME" Description="A date and time combination. The supported range is \a1000-01-01 00:00:00\a to \a9999-12-31 23:59:59\a." ParamCount="0" OptionCount="0" ParamRequired="0" EditParamsAsString="0" SynonymGroup="0" PhysicalMapping="0" PhysicalTypeName="" >
</DATATYPE>
<DATATYPE ID="16" IDGroup="1" TypeName="TIMESTAMP" Description="A timestamp. The range is \a1970-01-01 00:00:00\a to sometime in the year 2037. The length can be 14 (or missing), 12, 10, 8, 6, 4, or 2 representing YYYYMMDDHHMMSS, ... , YYYYMMDD, ... , YY formats." ParamCount="1" OptionCount="0" ParamRequired="0" EditParamsAsString="0" SynonymGroup="0" PhysicalMapping="0" PhysicalTypeName="" >
<PARAMS>
<PARAM Name="length" />
</PARAMS>
</DATATYPE>
<DATATYPE ID="17" IDGroup="1" TypeName="TIME" Description="A time. The range is \a-838:59:59\a to \a838:59:59\a." ParamCount="0" OptionCount="0" ParamRequired="0" EditParamsAsString="0" SynonymGroup="0" PhysicalMapping="0" PhysicalTypeName="" >
</DATATYPE>
<DATATYPE ID="18" IDGroup="1" TypeName="YEAR" Description="A year in 2- or 4-digit format (default is 4-digit)." ParamCount="1" OptionCount="0" ParamRequired="0" EditParamsAsString="0" SynonymGroup="0" PhysicalMapping="0" PhysicalTypeName="" >
<PARAMS>
<PARAM Name="length" />
</PARAMS>
</DATATYPE>
<DATATYPE ID="19" IDGroup="2" TypeName="CHAR" Description="A fixed-length string (1 to 255 characters) that is always right-padded with spaces to the specified length when stored. values are sorted and compared in case-insensitive fashion according to the default character set unless the BINARY keyword is given." ParamCount="1" OptionCount="1" ParamRequired="1" EditParamsAsString="0" SynonymGroup="0" PhysicalMapping="0" PhysicalTypeName="" >
<PARAMS>
<PARAM Name="length" />
</PARAMS>
<OPTIONS>
<OPTION Name="BINARY" Default="0" />
</OPTIONS>
</DATATYPE>
<DATATYPE ID="20" IDGroup="2" TypeName="VARCHAR" Description="A variable-length string (1 to 255 characters). Values are sorted and compared in case-sensitive fashion unless the BINARY keyword is given." ParamCount="1" OptionCount="1" ParamRequired="1" EditParamsAsString="0" SynonymGroup="0" PhysicalMapping="0" PhysicalTypeName="" >
<PARAMS>
<PARAM Name="length" />
</PARAMS>
<OPTIONS>
<OPTION Name="BINARY" Default="0" />
</OPTIONS>
</DATATYPE>
<DATATYPE ID="21" IDGroup="2" TypeName="BIT" Description="This is a synonym for CHAR(1)." ParamCount="0" OptionCount="0" ParamRequired="0" EditParamsAsString="0" SynonymGroup="0" PhysicalMapping="0" PhysicalTypeName="" >
</DATATYPE>
<DATATYPE ID="22" IDGroup="2" TypeName="BOOL" Description="This is a synonym for CHAR(1)." ParamCount="0" OptionCount="0" ParamRequired="0" EditParamsAsString="0" SynonymGroup="0" PhysicalMapping="0" PhysicalTypeName="" >
</DATATYPE>
<DATATYPE ID="23" IDGroup="3" TypeName="TINYBLOB" Description="A column maximum length of 255 (2^8 - 1) characters. Values are sorted and compared in case-sensitive fashion." ParamCount="0" OptionCount="0" ParamRequired="0" EditParamsAsString="0" SynonymGroup="0" PhysicalMapping="0" PhysicalTypeName="" >
</DATATYPE>
<DATATYPE ID="24" IDGroup="3" TypeName="BLOB" Description="A column maximum length of 65535 (2^16 - 1) characters. Values are sorted and compared in case-sensitive fashion." ParamCount="0" OptionCount="0" ParamRequired="0" EditParamsAsString="0" SynonymGroup="0" PhysicalMapping="0" PhysicalTypeName="" >
</DATATYPE>
<DATATYPE ID="25" IDGroup="3" TypeName="MEDIUMBLOB" Description="A column maximum length of 16777215 (2^24 - 1) characters. Values are sorted and compared in case-sensitive fashion." ParamCount="0" OptionCount="0" ParamRequired="0" EditParamsAsString="0" SynonymGroup="0" PhysicalMapping="0" PhysicalTypeName="" >
</DATATYPE>
<DATATYPE ID="26" IDGroup="3" TypeName="LONGBLOB" Description="A column maximum length of 4294967295 (2^32 - 1) characters. Values are sorted and compared in case-sensitive fashion." ParamCount="0" OptionCount="0" ParamRequired="0" EditParamsAsString="0" SynonymGroup="0" PhysicalMapping="0" PhysicalTypeName="" >
</DATATYPE>
<DATATYPE ID="27" IDGroup="3" TypeName="TINYTEXT" Description="A column maximum length of 255 (2^8 - 1) characters." ParamCount="0" OptionCount="0" ParamRequired="0" EditParamsAsString="0" SynonymGroup="0" PhysicalMapping="0" PhysicalTypeName="" >
</DATATYPE>
<DATATYPE ID="28" IDGroup="3" TypeName="TEXT" Description="A column maximum length of 65535 (2^16 - 1) characters." ParamCount="0" OptionCount="0" ParamRequired="0" EditParamsAsString="0" SynonymGroup="0" PhysicalMapping="0" PhysicalTypeName="" >
</DATATYPE>
<DATATYPE ID="29" IDGroup="3" TypeName="MEDIUMTEXT" Description="A column maximum length of 16777215 (2^24 - 1) characters." ParamCount="0" OptionCount="0" ParamRequired="0" EditParamsAsString="0" SynonymGroup="0" PhysicalMapping="0" PhysicalTypeName="" >
</DATATYPE>
<DATATYPE ID="30" IDGroup="3" TypeName="LONGTEXT" Description="A column maximum length of 4294967295 (2^32 - 1) characters." ParamCount="0" OptionCount="0" ParamRequired="0" EditParamsAsString="0" SynonymGroup="0" PhysicalMapping="0" PhysicalTypeName="" >
</DATATYPE>
<DATATYPE ID="31" IDGroup="3" TypeName="ENUM" Description="An enumeration. A string object that can have only one value, chosen from the list of values." ParamCount="1" OptionCount="0" ParamRequired="1" EditParamsAsString="1" SynonymGroup="0" PhysicalMapping="0" PhysicalTypeName="" >
<PARAMS>
<PARAM Name="values" />
</PARAMS>
</DATATYPE>
<DATATYPE ID="32" IDGroup="3" TypeName="SET" Description="A set. A string object that can have zero or more values, each of which must be chosen from the list of values." ParamCount="1" OptionCount="0" ParamRequired="1" EditParamsAsString="1" SynonymGroup="0" PhysicalMapping="0" PhysicalTypeName="" >
<PARAMS>
<PARAM Name="values" />
</PARAMS>
</DATATYPE>
<DATATYPE ID="33" IDGroup="4" TypeName="Varchar(20)" Description="" ParamCount="0" OptionCount="1" ParamRequired="0" EditParamsAsString="0" SynonymGroup="0" PhysicalMapping="0" PhysicalTypeName="" >
<OPTIONS>
<OPTION Name="BINARY" Default="0" />
</OPTIONS>
</DATATYPE>
<DATATYPE ID="34" IDGroup="4" TypeName="Varchar(45)" Description="" ParamCount="0" OptionCount="1" ParamRequired="0" EditParamsAsString="0" SynonymGroup="0" PhysicalMapping="0" PhysicalTypeName="" >
<OPTIONS>
<OPTION Name="BINARY" Default="0" />
</OPTIONS>
</DATATYPE>
<DATATYPE ID="35" IDGroup="4" TypeName="Varchar(255)" Description="" ParamCount="0" OptionCount="1" ParamRequired="0" EditParamsAsString="0" SynonymGroup="0" PhysicalMapping="0" PhysicalTypeName="" >
<OPTIONS>
<OPTION Name="BINARY" Default="0" />
</OPTIONS>
</DATATYPE>
<DATATYPE ID="36" IDGroup="5" TypeName="GEOMETRY" Description="Geographic Datatype" ParamCount="0" OptionCount="0" ParamRequired="0" EditParamsAsString="0" SynonymGroup="0" PhysicalMapping="0" PhysicalTypeName="" >
</DATATYPE>
<DATATYPE ID="38" IDGroup="5" TypeName="LINESTRING" Description="Geographic Datatype" ParamCount="0" OptionCount="0" ParamRequired="0" EditParamsAsString="0" SynonymGroup="0" PhysicalMapping="0" PhysicalTypeName="" >
</DATATYPE>
<DATATYPE ID="39" IDGroup="5" TypeName="POLYGON" Description="Geographic Datatype" ParamCount="0" OptionCount="0" ParamRequired="0" EditParamsAsString="0" SynonymGroup="0" PhysicalMapping="0" PhysicalTypeName="" >
</DATATYPE>
<DATATYPE ID="40" IDGroup="5" TypeName="MULTIPOINT" Description="Geographic Datatype" ParamCount="0" OptionCount="0" ParamRequired="0" EditParamsAsString="0" SynonymGroup="0" PhysicalMapping="0" PhysicalTypeName="" >
</DATATYPE>
<DATATYPE ID="41" IDGroup="5" TypeName="MULTILINESTRING" Description="Geographic Datatype" ParamCount="0" OptionCount="0" ParamRequired="0" EditParamsAsString="0" SynonymGroup="0" PhysicalMapping="0" PhysicalTypeName="" >
</DATATYPE>
<DATATYPE ID="42" IDGroup="5" TypeName="MULTIPOLYGON" Description="Geographic Datatype" ParamCount="0" OptionCount="0" ParamRequired="0" EditParamsAsString="0" SynonymGroup="0" PhysicalMapping="0" PhysicalTypeName="" >
</DATATYPE>
<DATATYPE ID="43" IDGroup="5" TypeName="GEOMETRYCOLLECTION" Description="Geographic Datatype" ParamCount="0" OptionCount="0" ParamRequired="0" EditParamsAsString="0" SynonymGroup="0" PhysicalMapping="0" PhysicalTypeName="" >
</DATATYPE>
</DATATYPES>
<COMMON_DATATYPES>
<COMMON_DATATYPE ID="5" />
<COMMON_DATATYPE ID="8" />
<COMMON_DATATYPE ID="20" />
<COMMON_DATATYPE ID="15" />
<COMMON_DATATYPE ID="22" />
<COMMON_DATATYPE ID="28" />
<COMMON_DATATYPE ID="26" />
<COMMON_DATATYPE ID="33" />
<COMMON_DATATYPE ID="34" />
<COMMON_DATATYPE ID="35" />
</COMMON_DATATYPES>
<TABLEPREFIXES>
<TABLEPREFIX Name="Default (no prefix)" />
</TABLEPREFIXES>
<REGIONCOLORS>
<REGIONCOLOR Color="Red=#FFEEEC" />
<REGIONCOLOR Color="Yellow=#FEFDED" />
<REGIONCOLOR Color="Green=#EAFFE5" />
<REGIONCOLOR Color="Cyan=#ECFDFF" />
<REGIONCOLOR Color="Blue=#F0F1FE" />
<REGIONCOLOR Color="Magenta=#FFEBFA" />
</REGIONCOLORS>
<POSITIONMARKERS>
<POSITIONMARKER ZoomFac="-1.0" X="0" Y="0" />
<POSITIONMARKER ZoomFac="-1.0" X="0" Y="0" />
<POSITIONMARKER ZoomFac="-1.0" X="0" Y="0" />
<POSITIONMARKER ZoomFac="-1.0" X="0" Y="0" />
<POSITIONMARKER ZoomFac="-1.0" X="0" Y="0" />
<POSITIONMARKER ZoomFac="-1.0" X="0" Y="0" />
<POSITIONMARKER ZoomFac="-1.0" X="0" Y="0" />
<POSITIONMARKER ZoomFac="-1.0" X="0" Y="0" />
<POSITIONMARKER ZoomFac="-1.0" X="0" Y="0" />
<POSITIONMARKER ZoomFac="-1.0" X="0" Y="0" />
<POSITIONMARKER ZoomFac="-1.0" X="0" Y="0" />
</POSITIONMARKERS>
</SETTINGS>
<METADATA>
<REGIONS>
</REGIONS>
<TABLES>
<TABLE ID="1114" Tablename="Pessoa" PrevTableName="Table_01" XPos="382" YPos="210" TableType="0" TablePrefix="0" nmTable="0" Temporary="0" UseStandardInserts="0" StandardInserts="\n" TableOptions="DelayKeyTblUpdates=0\nPackKeys=0\nRowChecksum=0\nRowFormat=0\nUseRaid=0\nRaidType=0\n" Comments="" Collapsed="0" IsLinkedObject="0" IDLinkedModel="-1" Obj_id_Linked="-1" OrderPos="2" >
<COLUMNS>
<COLUMN ID="1116" ColName="id_Pessoa" PrevColName="" Pos="0" idDatatype="5" DatatypeParams="" Width="-1" Prec="-1" PrimaryKey="1" NotNull="1" AutoInc="1" IsForeignKey="0" DefaultValue="" Comments="">
<OPTIONSELECTED>
<OPTIONSELECT Value="1" />
<OPTIONSELECT Value="0" />
</OPTIONSELECTED>
</COLUMN>
</COLUMNS>
<RELATIONS_START>
<RELATION_START ID="1137" />
<RELATION_START ID="1174" />
<RELATION_START ID="1223" />
<RELATION_START ID="1265" />
<RELATION_START ID="1271" />
</RELATIONS_START>
<INDICES>
<INDEX ID="1117" IndexName="PRIMARY" IndexKind="0" FKRefDef_Obj_id="-1">
<INDEXCOLUMNS>
<INDEXCOLUMN idColumn="1116" LengthParam="0" />
</INDEXCOLUMNS>
</INDEX>
</INDICES>
</TABLE>
<TABLE ID="1119" Tablename="Funcionario" PrevTableName="Table_02" XPos="465" YPos="377" TableType="0" TablePrefix="0" nmTable="0" Temporary="0" UseStandardInserts="0" StandardInserts="\n" TableOptions="DelayKeyTblUpdates=0\nPackKeys=0\nRowChecksum=0\nRowFormat=0\nUseRaid=0\nRaidType=0\n" Comments="" Collapsed="0" IsLinkedObject="0" IDLinkedModel="-1" Obj_id_Linked="-1" OrderPos="3" >
<COLUMNS>
<COLUMN ID="1121" ColName="id_Funcionario" PrevColName="" Pos="0" idDatatype="5" DatatypeParams="" Width="-1" Prec="-1" PrimaryKey="1" NotNull="1" AutoInc="1" IsForeignKey="0" DefaultValue="" Comments="">
<OPTIONSELECTED>
<OPTIONSELECT Value="1" />
<OPTIONSELECT Value="0" />
</OPTIONSELECTED>
</COLUMN>
<COLUMN ID="1276" ColName="id_Pessoa" PrevColName="" Pos="1" idDatatype="5" DatatypeParams="" Width="-1" Prec="-1" PrimaryKey="0" NotNull="1" AutoInc="0" IsForeignKey="1" DefaultValue="" Comments="">
<OPTIONSELECTED>
<OPTIONSELECT Value="1" />
<OPTIONSELECT Value="0" />
</OPTIONSELECTED>
</COLUMN>
<COLUMN ID="1244" ColName="id_Cargo" PrevColName="" Pos="1" idDatatype="5" DatatypeParams="" Width="-1" Prec="-1" PrimaryKey="0" NotNull="1" AutoInc="0" IsForeignKey="1" DefaultValue="" Comments="">
<OPTIONSELECTED>
<OPTIONSELECT Value="1" />
<OPTIONSELECT Value="0" />
</OPTIONSELECTED>
</COLUMN>
<COLUMN ID="1239" ColName="id_Setor" PrevColName="" Pos="1" idDatatype="5" DatatypeParams="" Width="-1" Prec="-1" PrimaryKey="0" NotNull="1" AutoInc="0" IsForeignKey="1" DefaultValue="" Comments="">
<OPTIONSELECTED>
<OPTIONSELECT Value="1" />
<OPTIONSELECT Value="0" />
</OPTIONSELECTED>
</COLUMN>
<COLUMN ID="1203" ColName="Data de Contrata\231\227o" PrevColName="" Pos="3" idDatatype="5" DatatypeParams="" Width="-1" Prec="-1" PrimaryKey="0" NotNull="0" AutoInc="0" IsForeignKey="0" DefaultValue="" Comments="">
<OPTIONSELECTED>
<OPTIONSELECT Value="1" />
<OPTIONSELECT Value="0" />
</OPTIONSELECTED>
</COLUMN>
<COLUMN ID="1205" ColName="Numero de CTPS" PrevColName="" Pos="4" idDatatype="5" DatatypeParams="" Width="-1" Prec="-1" PrimaryKey="0" NotNull="0" AutoInc="0" IsForeignKey="0" DefaultValue="" Comments="">
<OPTIONSELECTED>
<OPTIONSELECT Value="1" />
<OPTIONSELECT Value="0" />
</OPTIONSELECTED>
</COLUMN>
<COLUMN ID="1206" ColName="Salario Atual" PrevColName="" Pos="5" idDatatype="5" DatatypeParams="" Width="-1" Prec="-1" PrimaryKey="0" NotNull="0" AutoInc="0" IsForeignKey="0" DefaultValue="" Comments="">
<OPTIONSELECTED>
<OPTIONSELECT Value="1" />
<OPTIONSELECT Value="0" />
</OPTIONSELECTED>
</COLUMN>
<COLUMN ID="1207" ColName="Percentual de Reazuste" PrevColName="" Pos="6" idDatatype="7" DatatypeParams="" Width="-1" Prec="-1" PrimaryKey="0" NotNull="0" AutoInc="0" IsForeignKey="0" DefaultValue="" Comments="">
<OPTIONSELECTED>
<OPTIONSELECT Value="0" />
</OPTIONSELECTED>
</COLUMN>
<COLUMN ID="1250" ColName="Comi\231\227o" PrevColName="" Pos="8" idDatatype="5" DatatypeParams="" Width="-1" Prec="-1" PrimaryKey="0" NotNull="0" AutoInc="0" IsForeignKey="0" DefaultValue="" Comments="">
<OPTIONSELECTED>
<OPTIONSELECT Value="1" />
<OPTIONSELECT Value="0" />
</OPTIONSELECTED>
</COLUMN>
</COLUMNS>
<RELATIONS_START>
<RELATION_START ID="1355" />
<RELATION_START ID="1366" />
<RELATION_START ID="1376" />
</RELATIONS_START>
<RELATIONS_END>
<RELATION_END ID="1232" />
<RELATION_END ID="1238" />
<RELATION_END ID="1243" />
</RELATIONS_END>
<INDICES>
<INDEX ID="1122" IndexName="PRIMARY" IndexKind="0" FKRefDef_Obj_id="-1">
<INDEXCOLUMNS>
<INDEXCOLUMN idColumn="1121" LengthParam="0" />
</INDEXCOLUMNS>
</INDEX>
<INDEX ID="1240" IndexName="Funcionario_FKIndex2" IndexKind="1" FKRefDef_Obj_id="1238">
<INDEXCOLUMNS>
<INDEXCOLUMN idColumn="1239" LengthParam="0" />
</INDEXCOLUMNS>
</INDEX>
<INDEX ID="1245" IndexName="Funcionario_FKIndex3" IndexKind="1" FKRefDef_Obj_id="1243">
<INDEXCOLUMNS>
<INDEXCOLUMN idColumn="1244" LengthParam="0" />
</INDEXCOLUMNS>
</INDEX>
</INDICES>
</TABLE>
<TABLE ID="1127" Tablename="Endere\231o" PrevTableName="Table_03" XPos="111" YPos="35" TableType="0" TablePrefix="0" nmTable="0" Temporary="0" UseStandardInserts="0" StandardInserts="\n" TableOptions="DelayKeyTblUpdates=0\nPackKeys=0\nRowChecksum=0\nRowFormat=0\nUseRaid=0\nRaidType=0\n" Comments="" Collapsed="0" IsLinkedObject="0" IDLinkedModel="-1" Obj_id_Linked="-1" OrderPos="5" >
<COLUMNS>
<COLUMN ID="1129" ColName="id_Endere\231o" PrevColName="" Pos="0" idDatatype="5" DatatypeParams="" Width="-1" Prec="-1" PrimaryKey="1" NotNull="1" AutoInc="1" IsForeignKey="0" DefaultValue="" Comments="">
<OPTIONSELECTED>
<OPTIONSELECT Value="1" />
<OPTIONSELECT Value="0" />
</OPTIONSELECTED>
</COLUMN>
<COLUMN ID="1138" ColName="Pessoa_id_Pessoa" PrevColName="" Pos="1" idDatatype="5" DatatypeParams="" Width="-1" Prec="-1" PrimaryKey="1" NotNull="1" AutoInc="0" IsForeignKey="1" DefaultValue="" Comments="">
<OPTIONSELECTED>
<OPTIONSELECT Value="1" />
<OPTIONSELECT Value="0" />
</OPTIONSELECTED>
</COLUMN>
<COLUMN ID="1131" ColName="Logradouro" PrevColName="" Pos="1" idDatatype="5" DatatypeParams="" Width="-1" Prec="-1" PrimaryKey="0" NotNull="0" AutoInc="0" IsForeignKey="0" DefaultValue="" Comments="">
<OPTIONSELECTED>
<OPTIONSELECT Value="1" />
<OPTIONSELECT Value="0" />
</OPTIONSELECTED>
</COLUMN>
<COLUMN ID="1135" ColName="Numero" PrevColName="" Pos="5" idDatatype="5" DatatypeParams="" Width="-1" Prec="-1" PrimaryKey="0" NotNull="0" AutoInc="0" IsForeignKey="0" DefaultValue="" Comments="">
<OPTIONSELECTED>
<OPTIONSELECT Value="1" />
<OPTIONSELECT Value="0" />
</OPTIONSELECTED>
</COLUMN>
<COLUMN ID="1132" ColName="CEP" PrevColName="" Pos="2" idDatatype="5" DatatypeParams="" Width="-1" Prec="-1" PrimaryKey="0" NotNull="0" AutoInc="0" IsForeignKey="0" DefaultValue="" Comments="">
<OPTIONSELECTED>
<OPTIONSELECT Value="1" />
<OPTIONSELECT Value="0" />
</OPTIONSELECTED>
</COLUMN>
<COLUMN ID="1133" ColName="UF" PrevColName="" Pos="3" idDatatype="20" DatatypeParams="" Width="-1" Prec="-1" PrimaryKey="0" NotNull="0" AutoInc="0" IsForeignKey="0" DefaultValue="" Comments="">
<OPTIONSELECTED>
<OPTIONSELECT Value="0" />
</OPTIONSELECTED>
</COLUMN>
<COLUMN ID="1134" ColName="Cidade" PrevColName="" Pos="4" idDatatype="20" DatatypeParams="" Width="-1" Prec="-1" PrimaryKey="0" NotNull="0" AutoInc="0" IsForeignKey="0" DefaultValue="" Comments="">
<OPTIONSELECTED>
<OPTIONSELECT Value="0" />
</OPTIONSELECTED>
</COLUMN>
<COLUMN ID="1136" ColName="Bairro" PrevColName="" Pos="6" idDatatype="20" DatatypeParams="" Width="-1" Prec="-1" PrimaryKey="0" NotNull="0" AutoInc="0" IsForeignKey="0" DefaultValue="" Comments="">
<OPTIONSELECTED>
<OPTIONSELECT Value="0" />
</OPTIONSELECTED>
</COLUMN>
</COLUMNS>
<RELATIONS_END>
<RELATION_END ID="1137" />
</RELATIONS_END>
<INDICES>
<INDEX ID="1130" IndexName="PRIMARY" IndexKind="0" FKRefDef_Obj_id="-1">
<INDEXCOLUMNS>
<INDEXCOLUMN idColumn="1129" LengthParam="0" />
<INDEXCOLUMN idColumn="1138" LengthParam="0" />
</INDEXCOLUMNS>
</INDEX>
<INDEX ID="1139" IndexName="Endere\231o_FKIndex1" IndexKind="1" FKRefDef_Obj_id="1137">
<INDEXCOLUMNS>
<INDEXCOLUMN idColumn="1138" LengthParam="0" />
</INDEXCOLUMNS>
</INDEX>
</INDICES>
</TABLE>
<TABLE ID="1140" Tablename="Pessoa Fisica" PrevTableName="Table_04" XPos="92" YPos="453" TableType="0" TablePrefix="0" nmTable="0" Temporary="0" UseStandardInserts="0" StandardInserts="\n" TableOptions="DelayKeyTblUpdates=0\nPackKeys=0\nRowChecksum=0\nRowFormat=0\nUseRaid=0\nRaidType=0\n" Comments="" Collapsed="0" IsLinkedObject="0" IDLinkedModel="-1" Obj_id_Linked="-1" OrderPos="6" >
<COLUMNS>
<COLUMN ID="1272" ColName="id_Pessoa" PrevColName="" Pos="1" idDatatype="5" DatatypeParams="" Width="-1" Prec="-1" PrimaryKey="1" NotNull="1" AutoInc="0" IsForeignKey="1" DefaultValue="" Comments="">
<OPTIONSELECTED>
<OPTIONSELECT Value="1" />
<OPTIONSELECT Value="0" />
</OPTIONSELECTED>
</COLUMN>
<COLUMN ID="1278" ColName="Nome" PrevColName="" Pos="4" idDatatype="20" DatatypeParams="" Width="-1" Prec="-1" PrimaryKey="0" NotNull="0" AutoInc="0" IsForeignKey="0" DefaultValue="" Comments="">
<OPTIONSELECTED>
<OPTIONSELECT Value="0" />
</OPTIONSELECTED>
</COLUMN>
<COLUMN ID="1162" ColName="RG" PrevColName="" Pos="2" idDatatype="5" DatatypeParams="" Width="-1" Prec="-1" PrimaryKey="0" NotNull="1" AutoInc="0" IsForeignKey="0" DefaultValue="" Comments="">
<OPTIONSELECTED>
<OPTIONSELECT Value="1" />
<OPTIONSELECT Value="0" />
</OPTIONSELECTED>
</COLUMN>
<COLUMN ID="1163" ColName="CPF" PrevColName="" Pos="3" idDatatype="5" DatatypeParams="" Width="-1" Prec="-1" PrimaryKey="0" NotNull="0" AutoInc="0" IsForeignKey="0" DefaultValue="" Comments="">
<OPTIONSELECTED>
<OPTIONSELECT Value="1" />
<OPTIONSELECT Value="0" />
</OPTIONSELECTED>
</COLUMN>
<COLUMN ID="1165" ColName="Data de Nasc." PrevColName="" Pos="4" idDatatype="14" DatatypeParams="" Width="-1" Prec="-1" PrimaryKey="0" NotNull="0" AutoInc="0" IsForeignKey="0" DefaultValue="" Comments="">
<OPTIONSELECTED>
</OPTIONSELECTED>
</COLUMN>
<COLUMN ID="1280" ColName="E-mail" PrevColName="" Pos="5" idDatatype="20" DatatypeParams="" Width="-1" Prec="-1" PrimaryKey="0" NotNull="0" AutoInc="0" IsForeignKey="0" DefaultValue="" Comments="">
<OPTIONSELECTED>
<OPTIONSELECT Value="0" />
</OPTIONSELECTED>
</COLUMN>
<COLUMN ID="1282" ColName="Data de Cadastro" PrevColName="" Pos="6" idDatatype="14" DatatypeParams="" Width="-1" Prec="-1" PrimaryKey="0" NotNull="0" AutoInc="0" IsForeignKey="0" DefaultValue="" Comments="">
<OPTIONSELECTED>
</OPTIONSELECTED>
</COLUMN>
</COLUMNS>
<RELATIONS_START>
<RELATION_START ID="1232" />
<RELATION_START ID="1292" />
</RELATIONS_START>
<RELATIONS_END>
<RELATION_END ID="1271" />
</RELATIONS_END>
<INDICES>
<INDEX ID="1274" IndexName="PRIMARY" IndexKind="0" FKRefDef_Obj_id="-1">
<INDEXCOLUMNS>
<INDEXCOLUMN idColumn="1272" LengthParam="0" />
</INDEXCOLUMNS>
</INDEX>
<INDEX ID="1273" IndexName="Pessoa Fisica_FKIndex1" IndexKind="1" FKRefDef_Obj_id="1271">
<INDEXCOLUMNS>
<INDEXCOLUMN idColumn="1272" LengthParam="0" />
</INDEXCOLUMNS>
</INDEX>
</INDICES>
</TABLE>
<TABLE ID="1141" Tablename="Pessoa Juridica" PrevTableName="Table_05" XPos="461" YPos="41" TableType="0" TablePrefix="0" nmTable="0" Temporary="0" UseStandardInserts="0" StandardInserts="\n" TableOptions="DelayKeyTblUpdates=0\nPackKeys=0\nRowChecksum=0\nRowFormat=0\nUseRaid=0\nRaidType=0\n" Comments="" Collapsed="0" IsLinkedObject="0" IDLinkedModel="-1" Obj_id_Linked="-1" OrderPos="7" >
<COLUMNS>
<COLUMN ID="1266" ColName="id_Pessoa" PrevColName="" Pos="1" idDatatype="5" DatatypeParams="" Width="-1" Prec="-1" PrimaryKey="1" NotNull="1" AutoInc="0" IsForeignKey="1" DefaultValue="" Comments="">
<OPTIONSELECTED>
<OPTIONSELECT Value="1" />
<OPTIONSELECT Value="0" />
</OPTIONSELECTED>
</COLUMN>
<COLUMN ID="1284" ColName="Raz\227o Social" PrevColName="" Pos="1" idDatatype="20" DatatypeParams="" Width="-1" Prec="-1" PrimaryKey="0" NotNull="0" AutoInc="0" IsForeignKey="0" DefaultValue="" Comments="">
<OPTIONSELECTED>
<OPTIONSELECT Value="0" />
</OPTIONSELECTED>
</COLUMN>
<COLUMN ID="1285" ColName="Nome Fantasia" PrevColName="" Pos="2" idDatatype="20" DatatypeParams="" Width="-1" Prec="-1" PrimaryKey="0" NotNull="0" AutoInc="0" IsForeignKey="0" DefaultValue="" Comments="">
<OPTIONSELECTED>
<OPTIONSELECT Value="0" />
</OPTIONSELECTED>
</COLUMN>
<COLUMN ID="1286" ColName="CNPJ" PrevColName="" Pos="3" idDatatype="5" DatatypeParams="" Width="-1" Prec="-1" PrimaryKey="0" NotNull="0" AutoInc="0" IsForeignKey="0" DefaultValue="" Comments="">
<OPTIONSELECTED>
<OPTIONSELECT Value="1" />
<OPTIONSELECT Value="0" />
</OPTIONSELECTED>
</COLUMN>
<COLUMN ID="1287" ColName="Data de Cadastro" PrevColName="" Pos="4" idDatatype="14" DatatypeParams="" Width="-1" Prec="-1" PrimaryKey="0" NotNull="0" AutoInc="0" IsForeignKey="0" DefaultValue="" Comments="">
<OPTIONSELECTED>
</OPTIONSELECTED>
</COLUMN>
</COLUMNS>
<RELATIONS_END>
<RELATION_END ID="1265" />
</RELATIONS_END>
<INDICES>
<INDEX ID="1269" IndexName="PRIMARY" IndexKind="0" FKRefDef_Obj_id="-1">
<INDEXCOLUMNS>
<INDEXCOLUMN idColumn="1266" LengthParam="0" />
</INDEXCOLUMNS>
</INDEX>
<INDEX ID="1268" IndexName="Pessoa Juridica_FKIndex1" IndexKind="1" FKRefDef_Obj_id="1265">
<INDEXCOLUMNS>
<INDEXCOLUMN idColumn="1266" LengthParam="0" />
</INDEXCOLUMNS>
</INDEX>
</INDICES>
</TABLE>
<TABLE ID="1166" Tablename="Telefone" PrevTableName="Table_06" XPos="67" YPos="241" TableType="0" TablePrefix="0" nmTable="0" Temporary="0" UseStandardInserts="0" StandardInserts="\n" TableOptions="DelayKeyTblUpdates=0\nPackKeys=0\nRowChecksum=0\nRowFormat=0\nUseRaid=0\nRaidType=0\n" Comments="" Collapsed="0" IsLinkedObject="0" IDLinkedModel="-1" Obj_id_Linked="-1" OrderPos="11" >
<COLUMNS>
<COLUMN ID="1168" ColName="id_Telefone" PrevColName="" Pos="0" idDatatype="5" DatatypeParams="" Width="-1" Prec="-1" PrimaryKey="1" NotNull="1" AutoInc="1" IsForeignKey="0" DefaultValue="" Comments="">
<OPTIONSELECTED>
<OPTIONSELECT Value="1" />
<OPTIONSELECT Value="0" />
</OPTIONSELECTED>
</COLUMN>
<COLUMN ID="1175" ColName="id_Pessoa" PrevColName="" Pos="1" idDatatype="5" DatatypeParams="" Width="-1" Prec="-1" PrimaryKey="1" NotNull="1" AutoInc="0" IsForeignKey="1" DefaultValue="" Comments="">
<OPTIONSELECTED>
<OPTIONSELECT Value="1" />
<OPTIONSELECT Value="0" />
</OPTIONSELECTED>
</COLUMN>
<COLUMN ID="1171" ColName="Celular" PrevColName="" Pos="1" idDatatype="5" DatatypeParams="" Width="-1" Prec="-1" PrimaryKey="0" NotNull="0" AutoInc="0" IsForeignKey="0" DefaultValue="" Comments="">
<OPTIONSELECTED>
<OPTIONSELECT Value="1" />
<OPTIONSELECT Value="0" />
</OPTIONSELECTED>
</COLUMN>
<COLUMN ID="1172" ColName="Residencial" PrevColName="" Pos="2" idDatatype="5" DatatypeParams="" Width="-1" Prec="-1" PrimaryKey="0" NotNull="0" AutoInc="0" IsForeignKey="0" DefaultValue="" Comments="">
<OPTIONSELECTED>
<OPTIONSELECT Value="1" />
<OPTIONSELECT Value="0" />
</OPTIONSELECTED>
</COLUMN>
<COLUMN ID="1173" ColName="Comecial" PrevColName="" Pos="3" idDatatype="5" DatatypeParams="" Width="-1" Prec="-1" PrimaryKey="0" NotNull="0" AutoInc="0" IsForeignKey="0" DefaultValue="" Comments="">
<OPTIONSELECTED>
<OPTIONSELECT Value="1" />
<OPTIONSELECT Value="0" />
</OPTIONSELECTED>
</COLUMN>
</COLUMNS>
<RELATIONS_END>
<RELATION_END ID="1174" />
</RELATIONS_END>
<INDICES>
<INDEX ID="1169" IndexName="PRIMARY" IndexKind="0" FKRefDef_Obj_id="-1">
<INDEXCOLUMNS>
<INDEXCOLUMN idColumn="1168" LengthParam="0" />
<INDEXCOLUMN idColumn="1175" LengthParam="0" />
</INDEXCOLUMNS>
</INDEX>
<INDEX ID="1176" IndexName="Telefone_FKIndex1" IndexKind="1" FKRefDef_Obj_id="1174">
<INDEXCOLUMNS>
<INDEXCOLUMN idColumn="1175" LengthParam="0" />
</INDEXCOLUMNS>
</INDEX>
</INDICES>
</TABLE>
<TABLE ID="1177" Tablename="Cliente" PrevTableName="Table_07" XPos="794" YPos="36" TableType="0" TablePrefix="0" nmTable="0" Temporary="0" UseStandardInserts="0" StandardInserts="\n" TableOptions="DelayKeyTblUpdates=0\nPackKeys=0\nRowChecksum=0\nRowFormat=0\nUseRaid=0\nRaidType=0\n" Comments="" Collapsed="0" IsLinkedObject="0" IDLinkedModel="-1" Obj_id_Linked="-1" OrderPos="13" >
<COLUMNS>
<COLUMN ID="1179" ColName="id_Cliente" PrevColName="" Pos="0" idDatatype="5" DatatypeParams="" Width="-1" Prec="-1" PrimaryKey="1" NotNull="1" AutoInc="1" IsForeignKey="0" DefaultValue="" Comments="">
<OPTIONSELECTED>
<OPTIONSELECT Value="1" />
<OPTIONSELECT Value="0" />
</OPTIONSELECTED>
</COLUMN>
<COLUMN ID="1322" ColName="id_Veiculos" PrevColName="" Pos="1" idDatatype="5" DatatypeParams="" Width="-1" Prec="-1" PrimaryKey="0" NotNull="1" AutoInc="0" IsForeignKey="1" DefaultValue="" Comments="">
<OPTIONSELECTED>
<OPTIONSELECT Value="1" />
<OPTIONSELECT Value="0" />
</OPTIONSELECTED>
</COLUMN>
<COLUMN ID="1315" ColName="id_Pessoa" PrevColName="" Pos="1" idDatatype="5" DatatypeParams="" Width="-1" Prec="-1" PrimaryKey="0" NotNull="1" AutoInc="0" IsForeignKey="1" DefaultValue="" Comments="">
<OPTIONSELECTED>
<OPTIONSELECT Value="1" />
<OPTIONSELECT Value="0" />
</OPTIONSELECTED>
</COLUMN>
<COLUMN ID="1305" ColName="id_Pessoa_Contato" PrevColName="" Pos="1" idDatatype="5" DatatypeParams="" Width="-1" Prec="-1" PrimaryKey="0" NotNull="1" AutoInc="0" IsForeignKey="1" DefaultValue="" Comments="">
<OPTIONSELECTED>
<OPTIONSELECT Value="1" />
<OPTIONSELECT Value="0" />
</OPTIONSELECTED>
</COLUMN>
</COLUMNS>
<RELATIONS_START>
<RELATION_START ID="1352" />
</RELATIONS_START>
<RELATIONS_END>
<RELATION_END ID="1223" />
<RELATION_END ID="1304" />
<RELATION_END ID="1321" />
</RELATIONS_END>
<INDICES>
<INDEX ID="1180" IndexName="PRIMARY" IndexKind="0" FKRefDef_Obj_id="-1">
<INDEXCOLUMNS>
<INDEXCOLUMN idColumn="1179" LengthParam="0" />
</INDEXCOLUMNS>
</INDEX>
<INDEX ID="1306" IndexName="Cliente_FKIndex2" IndexKind="1" FKRefDef_Obj_id="1304">
<INDEXCOLUMNS>
<INDEXCOLUMN idColumn="1305" LengthParam="0" />
</INDEXCOLUMNS>
</INDEX>
<INDEX ID="1323" IndexName="Cliente_FKIndex2" IndexKind="1" FKRefDef_Obj_id="1321">
<INDEXCOLUMNS>
<INDEXCOLUMN idColumn="1322" LengthParam="0" />
</INDEXCOLUMNS>
</INDEX>
</INDICES>
</TABLE>
<TABLE ID="1208" Tablename="Setor" PrevTableName="Table_08" XPos="453" YPos="666" TableType="0" TablePrefix="0" nmTable="0" Temporary="0" UseStandardInserts="0" StandardInserts="\n" TableOptions="DelayKeyTblUpdates=0\nPackKeys=0\nRowChecksum=0\nRowFormat=0\nUseRaid=0\nRaidType=0\n" Comments="" Collapsed="0" IsLinkedObject="0" IDLinkedModel="-1" Obj_id_Linked="-1" OrderPos="15" >
<COLUMNS>
<COLUMN ID="1210" ColName="id_Setor" PrevColName="" Pos="0" idDatatype="5" DatatypeParams="" Width="-1" Prec="-1" PrimaryKey="1" NotNull="1" AutoInc="1" IsForeignKey="0" DefaultValue="" Comments="">
<OPTIONSELECTED>
<OPTIONSELECT Value="1" />
<OPTIONSELECT Value="0" />
</OPTIONSELECTED>
</COLUMN>
<COLUMN ID="1217" ColName="Nome" PrevColName="" Pos="1" idDatatype="5" DatatypeParams="" Width="-1" Prec="-1" PrimaryKey="0" NotNull="0" AutoInc="0" IsForeignKey="0" DefaultValue="" Comments="">
<OPTIONSELECTED>
<OPTIONSELECT Value="1" />
<OPTIONSELECT Value="0" />
</OPTIONSELECTED>
</COLUMN>
<COLUMN ID="1218" ColName="Sigla" PrevColName="" Pos="2" idDatatype="5" DatatypeParams="" Width="-1" Prec="-1" PrimaryKey="0" NotNull="0" AutoInc="0" IsForeignKey="0" DefaultValue="" Comments="">
<OPTIONSELECTED>
<OPTIONSELECT Value="1" />
<OPTIONSELECT Value="0" />
</OPTIONSELECTED>
</COLUMN>
<COLUMN ID="1219" ColName="Encarregado" PrevColName="" Pos="3" idDatatype="20" DatatypeParams="" Width="-1" Prec="-1" PrimaryKey="0" NotNull="0" AutoInc="0" IsForeignKey="0" DefaultValue="" Comments="">
<OPTIONSELECTED>
<OPTIONSELECT Value="0" />
</OPTIONSELECTED>
</COLUMN>
</COLUMNS>
<RELATIONS_START>
<RELATION_START ID="1220" />
<RELATION_START ID="1238" />
<RELATION_START ID="1345" />
</RELATIONS_START>
<INDICES>
<INDEX ID="1211" IndexName="PRIMARY" IndexKind="0" FKRefDef_Obj_id="-1">
<INDEXCOLUMNS>
<INDEXCOLUMN idColumn="1210" LengthParam="0" />
</INDEXCOLUMNS>
</INDEX>
</INDICES>
</TABLE>
<TABLE ID="1212" Tablename="Cargo" PrevTableName="Table_09" XPos="175" YPos="633" TableType="0" TablePrefix="0" nmTable="0" Temporary="0" UseStandardInserts="0" StandardInserts="\n" TableOptions="DelayKeyTblUpdates=0\nPackKeys=0\nRowChecksum=0\nRowFormat=0\nUseRaid=0\nRaidType=0\n" Comments="" Collapsed="0" IsLinkedObject="0" IDLinkedModel="-1" Obj_id_Linked="-1" OrderPos="16" >
<COLUMNS>
<COLUMN ID="1214" ColName="id_Cargo" PrevColName="" Pos="0" idDatatype="5" DatatypeParams="" Width="-1" Prec="-1" PrimaryKey="1" NotNull="1" AutoInc="1" IsForeignKey="0" DefaultValue="" Comments="">
<OPTIONSELECTED>
<OPTIONSELECT Value="1" />
<OPTIONSELECT Value="0" />
</OPTIONSELECTED>
</COLUMN>
<COLUMN ID="1221" ColName="id_Setor" PrevColName="" Pos="1" idDatatype="5" DatatypeParams="" Width="-1" Prec="-1" PrimaryKey="0" NotNull="1" AutoInc="0" IsForeignKey="1" DefaultValue="" Comments="">
<OPTIONSELECTED>
<OPTIONSELECT Value="1" />
<OPTIONSELECT Value="0" />
</OPTIONSELECTED>
</COLUMN>
<COLUMN ID="1247" ColName="Comi\231\227o" PrevColName="" Pos="3" idDatatype="5" DatatypeParams="" Width="-1" Prec="-1" PrimaryKey="0" NotNull="1" AutoInc="0" IsForeignKey="0" DefaultValue="" Comments="">
<OPTIONSELECTED>
<OPTIONSELECT Value="1" />
<OPTIONSELECT Value="0" />
</OPTIONSELECTED>
</COLUMN>
<COLUMN ID="1242" ColName="Nome" PrevColName="" Pos="2" idDatatype="20" DatatypeParams="" Width="-1" Prec="-1" PrimaryKey="0" NotNull="0" AutoInc="0" IsForeignKey="0" DefaultValue="" Comments="">
<OPTIONSELECTED>
<OPTIONSELECT Value="0" />
</OPTIONSELECTED>
</COLUMN>
</COLUMNS>
<RELATIONS_START>
<RELATION_START ID="1243" />
</RELATIONS_START>
<RELATIONS_END>
<RELATION_END ID="1220" />
</RELATIONS_END>
<INDICES>
<INDEX ID="1215" IndexName="PRIMARY" IndexKind="0" FKRefDef_Obj_id="-1">
<INDEXCOLUMNS>
<INDEXCOLUMN idColumn="1214" LengthParam="0" />
</INDEXCOLUMNS>
</INDEX>
<INDEX ID="1222" IndexName="Cargo_FKIndex1" IndexKind="1" FKRefDef_Obj_id="1220">
<INDEXCOLUMNS>
<INDEXCOLUMN idColumn="1221" LengthParam="0" />
</INDEXCOLUMNS>
</INDEX>
</INDICES>
</TABLE>
<TABLE ID="1288" Tablename="Pessoas Contato" PrevTableName="Table_10" XPos="562" YPos="282" TableType="0" TablePrefix="0" nmTable="0" Temporary="0" UseStandardInserts="0" StandardInserts="\n" TableOptions="DelayKeyTblUpdates=0\nPackKeys=0\nRowChecksum=0\nRowFormat=0\nUseRaid=0\nRaidType=0\n" Comments="" Collapsed="0" IsLinkedObject="0" IDLinkedModel="-1" Obj_id_Linked="-1" OrderPos="20" >
<COLUMNS>
<COLUMN ID="1297" ColName="id_Pessoa_Contato" PrevColName="" Pos="1" idDatatype="5" DatatypeParams="" Width="-1" Prec="-1" PrimaryKey="1" NotNull="1" AutoInc="0" IsForeignKey="0" DefaultValue="" Comments="">
<OPTIONSELECTED>
<OPTIONSELECT Value="1" />
<OPTIONSELECT Value="0" />
</OPTIONSELECTED>
</COLUMN>
<COLUMN ID="1293" ColName="id_Pessoa" PrevColName="" Pos="1" idDatatype="5" DatatypeParams="" Width="-1" Prec="-1" PrimaryKey="0" NotNull="1" AutoInc="0" IsForeignKey="1" DefaultValue="" Comments="">
<OPTIONSELECTED>
<OPTIONSELECT Value="1" />
<OPTIONSELECT Value="0" />
</OPTIONSELECTED>
</COLUMN>
</COLUMNS>
<RELATIONS_START>
<RELATION_START ID="1304" />
</RELATIONS_START>
<RELATIONS_END>
<RELATION_END ID="1292" />
</RELATIONS_END>
<INDICES>
<INDEX ID="1298" IndexName="PRIMARY" IndexKind="0" FKRefDef_Obj_id="-1">
<INDEXCOLUMNS>
<INDEXCOLUMN idColumn="1297" LengthParam="0" />
</INDEXCOLUMNS>
</INDEX>
<INDEX ID="1294" IndexName="P_Contato_FKIndex1" IndexKind="1" FKRefDef_Obj_id="1292">
<INDEXCOLUMNS>
<INDEXCOLUMN idColumn="1293" LengthParam="0" />
</INDEXCOLUMNS>
</INDEX>
</INDICES>
</TABLE>
<TABLE ID="1317" Tablename="Veiculos" PrevTableName="Table_11" XPos="1228" YPos="40" TableType="0" TablePrefix="0" nmTable="0" Temporary="0" UseStandardInserts="0" StandardInserts="\n" TableOptions="DelayKeyTblUpdates=0\nPackKeys=0\nRowChecksum=0\nRowFormat=0\nUseRaid=0\nRaidType=0\n" Comments="" Collapsed="0" IsLinkedObject="0" IDLinkedModel="-1" Obj_id_Linked="-1" OrderPos="23" >
<COLUMNS>
<COLUMN ID="1319" ColName="id_Veiculos" PrevColName="" Pos="0" idDatatype="5" DatatypeParams="" Width="-1" Prec="-1" PrimaryKey="1" NotNull="1" AutoInc="1" IsForeignKey="0" DefaultValue="" Comments="">
<OPTIONSELECTED>
<OPTIONSELECT Value="1" />
<OPTIONSELECT Value="0" />
</OPTIONSELECTED>
</COLUMN>
<COLUMN ID="1325" ColName="Marca" PrevColName="" Pos="1" idDatatype="20" DatatypeParams="" Width="-1" Prec="-1" PrimaryKey="0" NotNull="0" AutoInc="0" IsForeignKey="0" DefaultValue="" Comments="">
<OPTIONSELECTED>
<OPTIONSELECT Value="0" />
</OPTIONSELECTED>
</COLUMN>
<COLUMN ID="1326" ColName="Modelo" PrevColName="" Pos="2" idDatatype="20" DatatypeParams="" Width="-1" Prec="-1" PrimaryKey="0" NotNull="0" AutoInc="0" IsForeignKey="0" DefaultValue="" Comments="">
<OPTIONSELECTED>
<OPTIONSELECT Value="0" />
</OPTIONSELECTED>
</COLUMN>
<COLUMN ID="1327" ColName="Vers\227o" PrevColName="" Pos="3" idDatatype="20" DatatypeParams="" Width="-1" Prec="-1" PrimaryKey="0" NotNull="0" AutoInc="0" IsForeignKey="0" DefaultValue="" Comments="">
<OPTIONSELECTED>
<OPTIONSELECT Value="0" />
</OPTIONSELECTED>
</COLUMN>
<COLUMN ID="1329" ColName="Ano Modelo" PrevColName="" Pos="4" idDatatype="5" DatatypeParams="" Width="-1" Prec="-1" PrimaryKey="0" NotNull="0" AutoInc="0" IsForeignKey="0" DefaultValue="" Comments="">
<OPTIONSELECTED>
<OPTIONSELECT Value="1" />
<OPTIONSELECT Value="0" />
</OPTIONSELECTED>
</COLUMN>
<COLUMN ID="1330" ColName="Ano Fabrica\231\227o" PrevColName="" Pos="5" idDatatype="5" DatatypeParams="" Width="-1" Prec="-1" PrimaryKey="0" NotNull="0" AutoInc="0" IsForeignKey="0" DefaultValue="" Comments="">
<OPTIONSELECTED>
<OPTIONSELECT Value="1" />
<OPTIONSELECT Value="0" />
</OPTIONSELECTED>
</COLUMN>
<COLUMN ID="1332" ColName="Cor" PrevColName="" Pos="6" idDatatype="20" DatatypeParams="" Width="-1" Prec="-1" PrimaryKey="0" NotNull="0" AutoInc="0" IsForeignKey="0" DefaultValue="" Comments="">
<OPTIONSELECTED>
<OPTIONSELECT Value="0" />
</OPTIONSELECTED>
</COLUMN>
<COLUMN ID="1333" ColName="Combustivel" PrevColName="" Pos="7" idDatatype="20" DatatypeParams="" Width="-1" Prec="-1" PrimaryKey="0" NotNull="0" AutoInc="0" IsForeignKey="0" DefaultValue="" Comments="">
<OPTIONSELECTED>
<OPTIONSELECT Value="0" />
</OPTIONSELECTED>
</COLUMN>
<COLUMN ID="1335" ColName="Placa" PrevColName="" Pos="8" idDatatype="20" DatatypeParams="" Width="-1" Prec="-1" PrimaryKey="0" NotNull="0" AutoInc="0" IsForeignKey="0" DefaultValue="" Comments="">
<OPTIONSELECTED>
<OPTIONSELECT Value="0" />
</OPTIONSELECTED>
</COLUMN>
</COLUMNS>
<RELATIONS_START>
<RELATION_START ID="1321" />
</RELATIONS_START>
<INDICES>
<INDEX ID="1320" IndexName="PRIMARY" IndexKind="0" FKRefDef_Obj_id="-1">
<INDEXCOLUMNS>
<INDEXCOLUMN idColumn="1319" LengthParam="0" />
</INDEXCOLUMNS>
</INDEX>
</INDICES>
</TABLE>
<TABLE ID="1336" Tablename="Servi\231os" PrevTableName="Table_12" XPos="965" YPos="161" TableType="0" TablePrefix="0" nmTable="0" Temporary="0" UseStandardInserts="0" StandardInserts="\n" TableOptions="DelayKeyTblUpdates=0\nPackKeys=0\nRowChecksum=0\nRowFormat=0\nUseRaid=0\nRaidType=0\n" Comments="" Collapsed="0" IsLinkedObject="0" IDLinkedModel="-1" Obj_id_Linked="-1" OrderPos="25" >
<COLUMNS>
<COLUMN ID="1338" ColName="id_Servi\231os" PrevColName="" Pos="0" idDatatype="5" DatatypeParams="" Width="-1" Prec="-1" PrimaryKey="1" NotNull="1" AutoInc="1" IsForeignKey="0" DefaultValue="" Comments="">
<OPTIONSELECTED>
<OPTIONSELECT Value="1" />
<OPTIONSELECT Value="0" />
</OPTIONSELECTED>
</COLUMN>
<COLUMN ID="1430" ColName="Percentual de Desconto" PrevColName="" Pos="1" idDatatype="7" DatatypeParams="" Width="-1" Prec="-1" PrimaryKey="0" NotNull="1" AutoInc="0" IsForeignKey="1" DefaultValue="" Comments="">
<OPTIONSELECTED>
<OPTIONSELECT Value="0" />
</OPTIONSELECTED>
</COLUMN>
<COLUMN ID="1377" ColName="id_Funcionario" PrevColName="" Pos="1" idDatatype="5" DatatypeParams="" Width="-1" Prec="-1" PrimaryKey="0" NotNull="1" AutoInc="0" IsForeignKey="1" DefaultValue="" Comments="">
<OPTIONSELECTED>
<OPTIONSELECT Value="1" />
<OPTIONSELECT Value="0" />
</OPTIONSELECTED>
</COLUMN>
<COLUMN ID="1364" ColName="id_Ordem de Seri\231o" PrevColName="" Pos="1" idDatatype="5" DatatypeParams="" Width="-1" Prec="-1" PrimaryKey="0" NotNull="1" AutoInc="0" IsForeignKey="1" DefaultValue="" Comments="">
<OPTIONSELECTED>
<OPTIONSELECT Value="1" />
<OPTIONSELECT Value="0" />
</OPTIONSELECTED>
</COLUMN>
<COLUMN ID="1346" ColName="id_Setor" PrevColName="" Pos="1" idDatatype="5" DatatypeParams="" Width="-1" Prec="-1" PrimaryKey="0" NotNull="1" AutoInc="0" IsForeignKey="1" DefaultValue="" Comments="">
<OPTIONSELECTED>
<OPTIONSELECT Value="1" />
<OPTIONSELECT Value="0" />
</OPTIONSELECTED>
</COLUMN>
<COLUMN ID="1341" ColName="Nome" PrevColName="" Pos="1" idDatatype="20" DatatypeParams="" Width="-1" Prec="-1" PrimaryKey="0" NotNull="0" AutoInc="0" IsForeignKey="0" DefaultValue="" Comments="">
<OPTIONSELECTED>
<OPTIONSELECT Value="0" />
</OPTIONSELECTED>
</COLUMN>
<COLUMN ID="1342" ColName="Valor" PrevColName="" Pos="2" idDatatype="5" DatatypeParams="" Width="-1" Prec="-1" PrimaryKey="0" NotNull="0" AutoInc="0" IsForeignKey="0" DefaultValue="" Comments="">
<OPTIONSELECTED>
<OPTIONSELECT Value="1" />
<OPTIONSELECT Value="0" />
</OPTIONSELECTED>
</COLUMN>
<COLUMN ID="1344" ColName="Quantidade de Horas" PrevColName="" Pos="3" idDatatype="5" DatatypeParams="" Width="-1" Prec="-1" PrimaryKey="0" NotNull="0" AutoInc="0" IsForeignKey="0" DefaultValue="" Comments="">
<OPTIONSELECTED>
<OPTIONSELECT Value="1" />
<OPTIONSELECT Value="0" />
</OPTIONSELECTED>
</COLUMN>
</COLUMNS>
<RELATIONS_END>
<RELATION_END ID="1345" />
<RELATION_END ID="1363" />
<RELATION_END ID="1376" />
<RELATION_END ID="1429" />
</RELATIONS_END>
<INDICES>
<INDEX ID="1339" IndexName="PRIMARY" IndexKind="0" FKRefDef_Obj_id="-1">
<INDEXCOLUMNS>
<INDEXCOLUMN idColumn="1338" LengthParam="0" />
</INDEXCOLUMNS>
</INDEX>
<INDEX ID="1347" IndexName="Servi\231os_FKIndex1" IndexKind="1" FKRefDef_Obj_id="1345">
<INDEXCOLUMNS>
<INDEXCOLUMN idColumn="1346" LengthParam="0" />
</INDEXCOLUMNS>
</INDEX>
<INDEX ID="1365" IndexName="Servi\231os_FKIndex2" IndexKind="1" FKRefDef_Obj_id="1363">
<INDEXCOLUMNS>
<INDEXCOLUMN idColumn="1364" LengthParam="0" />
</INDEXCOLUMNS>
</INDEX>
<INDEX ID="1378" IndexName="Servi\231os_FKIndex3" IndexKind="1" FKRefDef_Obj_id="1376">
<INDEXCOLUMNS>
<INDEXCOLUMN idColumn="1377" LengthParam="0" />
</INDEXCOLUMNS>
</INDEX>
<INDEX ID="1431" IndexName="Servi\231os_FKIndex4" IndexKind="1" FKRefDef_Obj_id="1429">
<INDEXCOLUMNS>
<INDEXCOLUMN idColumn="1430" LengthParam="0" />
</INDEXCOLUMNS>
</INDEX>
</INDICES>
</TABLE>
<TABLE ID="1348" Tablename="Ordem de Seri\231o" PrevTableName="Table_13" XPos="841" YPos="493" TableType="0" TablePrefix="0" nmTable="0" Temporary="0" UseStandardInserts="0" StandardInserts="\n" TableOptions="DelayKeyTblUpdates=0\nPackKeys=0\nRowChecksum=0\nRowFormat=0\nUseRaid=0\nRaidType=0\n" Comments="" Collapsed="0" IsLinkedObject="0" IDLinkedModel="-1" Obj_id_Linked="-1" OrderPos="27" >
<COLUMNS>
<COLUMN ID="1350" ColName="id_Ordem de Seri\231o" PrevColName="" Pos="0" idDatatype="5" DatatypeParams="" Width="-1" Prec="-1" PrimaryKey="1" NotNull="1" AutoInc="1" IsForeignKey="0" DefaultValue="" Comments="">
<OPTIONSELECTED>
<OPTIONSELECT Value="1" />
<OPTIONSELECT Value="0" />
</OPTIONSELECTED>
</COLUMN>
<COLUMN ID="1440" ColName="Descri\231\227o" PrevColName="" Pos="1" idDatatype="20" DatatypeParams="" Width="-1" Prec="-1" PrimaryKey="0" NotNull="1" AutoInc="0" IsForeignKey="1" DefaultValue="" Comments="">
<OPTIONSELECTED>
<OPTIONSELECT Value="0" />
</OPTIONSELECTED>
</COLUMN>
<COLUMN ID="1356" ColName="id_Funcionario" PrevColName="" Pos="1" idDatatype="5" DatatypeParams="" Width="-1" Prec="-1" PrimaryKey="0" NotNull="1" AutoInc="0" IsForeignKey="1" DefaultValue="" Comments="">
<OPTIONSELECTED>
<OPTIONSELECT Value="1" />
<OPTIONSELECT Value="0" />
</OPTIONSELECTED>
</COLUMN>
<COLUMN ID="1353" ColName="id_Cliente" PrevColName="" Pos="1" idDatatype="5" DatatypeParams="" Width="-1" Prec="-1" PrimaryKey="0" NotNull="1" AutoInc="0" IsForeignKey="1" DefaultValue="" Comments="">
<OPTIONSELECTED>
<OPTIONSELECT Value="1" />
<OPTIONSELECT Value="0" />
</OPTIONSELECTED>
</COLUMN>
<COLUMN ID="1359" ColName="Descri\231\227o ou Servi\231o" PrevColName="" Pos="3" idDatatype="20" DatatypeParams="" Width="-1" Prec="-1" PrimaryKey="0" NotNull="0" AutoInc="0" IsForeignKey="0" DefaultValue="" Comments="">
<OPTIONSELECTED>
<OPTIONSELECT Value="0" />
</OPTIONSELECTED>
</COLUMN>
<COLUMN ID="1361" ColName="Data Chegada" PrevColName="Data_2" Pos="4" idDatatype="14" DatatypeParams="" Width="-1" Prec="-1" PrimaryKey="0" NotNull="0" AutoInc="0" IsForeignKey="0" DefaultValue="" Comments="">
<OPTIONSELECTED>
</OPTIONSELECTED>
</COLUMN>
<COLUMN ID="1369" ColName="Valor do Servi\231o" PrevColName="" Pos="5" idDatatype="5" DatatypeParams="" Width="-1" Prec="-1" PrimaryKey="0" NotNull="0" AutoInc="0" IsForeignKey="0" DefaultValue="" Comments="">
<OPTIONSELECTED>
<OPTIONSELECT Value="1" />
<OPTIONSELECT Value="0" />
</OPTIONSELECTED>
</COLUMN>
<COLUMN ID="1371" ColName="Data Inicio Servi\231o" PrevColName="" Pos="6" idDatatype="14" DatatypeParams="" Width="-1" Prec="-1" PrimaryKey="0" NotNull="0" AutoInc="0" IsForeignKey="0" DefaultValue="" Comments="">
<OPTIONSELECTED>
</OPTIONSELECTED>
</COLUMN>
<COLUMN ID="1373" ColName="Hora Inico Servi\231o" PrevColName="" Pos="7" idDatatype="5" DatatypeParams="" Width="-1" Prec="-1" PrimaryKey="0" NotNull="0" AutoInc="0" IsForeignKey="0" DefaultValue="" Comments="">
<OPTIONSELECTED>
<OPTIONSELECT Value="1" />
<OPTIONSELECT Value="0" />
</OPTIONSELECTED>
</COLUMN>
<COLUMN ID="1374" ColName="Data Final Servi\231o" PrevColName="" Pos="8" idDatatype="14" DatatypeParams="" Width="-1" Prec="-1" PrimaryKey="0" NotNull="0" AutoInc="0" IsForeignKey="0" DefaultValue="" Comments="">
<OPTIONSELECTED>
</OPTIONSELECTED>
</COLUMN>
<COLUMN ID="1375" ColName="Hora Final Servi\231o" PrevColName="" Pos="9" idDatatype="5" DatatypeParams="" Width="-1" Prec="-1" PrimaryKey="0" NotNull="0" AutoInc="0" IsForeignKey="0" DefaultValue="" Comments="">
<OPTIONSELECTED>
<OPTIONSELECT Value="1" />
<OPTIONSELECT Value="0" />
</OPTIONSELECTED>
</COLUMN>
</COLUMNS>
<RELATIONS_START>
<RELATION_START ID="1363" />
<RELATION_START ID="1385" />
<RELATION_START ID="1449" />
</RELATIONS_START>
<RELATIONS_END>
<RELATION_END ID="1352" />
<RELATION_END ID="1355" />
<RELATION_END ID="1366" />
<RELATION_END ID="1439" />
</RELATIONS_END>
<INDICES>
<INDEX ID="1351" IndexName="PRIMARY" IndexKind="0" FKRefDef_Obj_id="-1">
<INDEXCOLUMNS>
<INDEXCOLUMN idColumn="1350" LengthParam="0" />
</INDEXCOLUMNS>
</INDEX>
<INDEX ID="1354" IndexName="Ordem de Seri\231o_FKIndex1" IndexKind="1" FKRefDef_Obj_id="1352">
<INDEXCOLUMNS>
<INDEXCOLUMN idColumn="1353" LengthParam="0" />
</INDEXCOLUMNS>
</INDEX>
<INDEX ID="1357" IndexName="Ordem de Seri\231o_FKIndex2" IndexKind="1" FKRefDef_Obj_id="1355">
<INDEXCOLUMNS>
<INDEXCOLUMN idColumn="1356" LengthParam="0" />
</INDEXCOLUMNS>
</INDEX>
<INDEX ID="1367" IndexName="Ordem de Seri\231o_FKIndex3" IndexKind="1" FKRefDef_Obj_id="1366">
<INDEXCOLUMNS>
<INDEXCOLUMN idColumn="1356" LengthParam="0" />
</INDEXCOLUMNS>
</INDEX>
<INDEX ID="1441" IndexName="Ordem de Seri\231o_FKIndex4" IndexKind="1" FKRefDef_Obj_id="1439">
<INDEXCOLUMNS>
<INDEXCOLUMN idColumn="1440" LengthParam="0" />
</INDEXCOLUMNS>
</INDEX>
</INDICES>
</TABLE>
<TABLE ID="1379" Tablename="Pe\231as" PrevTableName="Table_14" XPos="941" YPos="804" TableType="0" TablePrefix="0" nmTable="0" Temporary="0" UseStandardInserts="0" StandardInserts="\n" TableOptions="DelayKeyTblUpdates=0\nPackKeys=0\nRowChecksum=0\nRowFormat=0\nUseRaid=0\nRaidType=0\n" Comments="" Collapsed="0" IsLinkedObject="0" IDLinkedModel="-1" Obj_id_Linked="-1" OrderPos="33" >
<COLUMNS>
<COLUMN ID="1381" ColName="id_Pe\231as" PrevColName="" Pos="0" idDatatype="5" DatatypeParams="" Width="-1" Prec="-1" PrimaryKey="1" NotNull="1" AutoInc="1" IsForeignKey="0" DefaultValue="" Comments="">
<OPTIONSELECTED>
<OPTIONSELECT Value="1" />
<OPTIONSELECT Value="0" />
</OPTIONSELECTED>
</COLUMN>
<COLUMN ID="1433" ColName="Percentual de Desconto" PrevColName="" Pos="1" idDatatype="7" DatatypeParams="" Width="-1" Prec="-1" PrimaryKey="0" NotNull="1" AutoInc="0" IsForeignKey="1" DefaultValue="" Comments="">
<OPTIONSELECTED>
<OPTIONSELECT Value="0" />
</OPTIONSELECTED>
</COLUMN>
<COLUMN ID="1395" ColName="Nome" PrevColName="" Pos="1" idDatatype="20" DatatypeParams="()" Width="-1" Prec="-1" PrimaryKey="0" NotNull="0" AutoInc="0" IsForeignKey="0" DefaultValue="" Comments="">
<OPTIONSELECTED>
<OPTIONSELECT Value="0" />
</OPTIONSELECTED>
</COLUMN>
<COLUMN ID="1396" ColName="Marca" PrevColName="" Pos="2" idDatatype="20" DatatypeParams="" Width="-1" Prec="-1" PrimaryKey="0" NotNull="0" AutoInc="0" IsForeignKey="0" DefaultValue="" Comments="">
<OPTIONSELECTED>
<OPTIONSELECT Value="0" />
</OPTIONSELECTED>
</COLUMN>
<COLUMN ID="1398" ColName="Valor" PrevColName="" Pos="3" idDatatype="5" DatatypeParams="" Width="-1" Prec="-1" PrimaryKey="0" NotNull="0" AutoInc="0" IsForeignKey="0" DefaultValue="" Comments="">
<OPTIONSELECTED>
<OPTIONSELECT Value="1" />
<OPTIONSELECT Value="0" />
</OPTIONSELECTED>
</COLUMN>
<COLUMN ID="1399" ColName="Quantidade Em Estoque" PrevColName="" Pos="4" idDatatype="5" DatatypeParams="" Width="-1" Prec="-1" PrimaryKey="0" NotNull="0" AutoInc="0" IsForeignKey="0" DefaultValue="" Comments="">
<OPTIONSELECTED>
<OPTIONSELECT Value="1" />
<OPTIONSELECT Value="0" />
</OPTIONSELECTED>
</COLUMN>
</COLUMNS>
<RELATIONS_START>
<RELATION_START ID="1384" />
</RELATIONS_START>
<RELATIONS_END>
<RELATION_END ID="1432" />
</RELATIONS_END>
<INDICES>
<INDEX ID="1382" IndexName="PRIMARY" IndexKind="0" FKRefDef_Obj_id="-1">
<INDEXCOLUMNS>
<INDEXCOLUMN idColumn="1381" LengthParam="0" />
</INDEXCOLUMNS>
</INDEX>
<INDEX ID="1434" IndexName="Pe\231as_FKIndex1" IndexKind="1" FKRefDef_Obj_id="1432">
<INDEXCOLUMNS>
<INDEXCOLUMN idColumn="1433" LengthParam="0" />
</INDEXCOLUMNS>
</INDEX>
</INDICES>
</TABLE>
<TABLE ID="1383" Tablename="Pe\231as_has_Ordem de Seri\231o" PrevTableName="" XPos="429" YPos="811" TableType="0" TablePrefix="0" nmTable="1" Temporary="0" UseStandardInserts="0" StandardInserts="\n" TableOptions="DelayKeyTblUpdates=0\nPackKeys=0\nRowChecksum=0\nRowFormat=0\nUseRaid=0\nRaidType=0\n" Comments="" Collapsed="0" IsLinkedObject="0" IDLinkedModel="-1" Obj_id_Linked="-1" OrderPos="34" >
<COLUMNS>
<COLUMN ID="1386" ColName="id_Pe\231as" PrevColName="" Pos="1" idDatatype="5" DatatypeParams="" Width="-1" Prec="-1" PrimaryKey="1" NotNull="1" AutoInc="0" IsForeignKey="1" DefaultValue="" Comments="">
<OPTIONSELECTED>
<OPTIONSELECT Value="1" />
<OPTIONSELECT Value="0" />
</OPTIONSELECTED>
</COLUMN>
<COLUMN ID="1388" ColName="id_Ordem de Seri\231o" PrevColName="" Pos="1" idDatatype="5" DatatypeParams="" Width="-1" Prec="-1" PrimaryKey="1" NotNull="1" AutoInc="0" IsForeignKey="1" DefaultValue="" Comments="">
<OPTIONSELECTED>
<OPTIONSELECT Value="1" />
<OPTIONSELECT Value="0" />
</OPTIONSELECTED>
</COLUMN>
<COLUMN ID="1392" ColName="Quantidade" PrevColName="" Pos="2" idDatatype="5" DatatypeParams="" Width="-1" Prec="-1" PrimaryKey="0" NotNull="0" AutoInc="0" IsForeignKey="0" DefaultValue="" Comments="">
<OPTIONSELECTED>
<OPTIONSELECT Value="1" />
<OPTIONSELECT Value="0" />
</OPTIONSELECTED>
</COLUMN>
<COLUMN ID="1393" ColName="Valor Unidade" PrevColName="" Pos="3" idDatatype="5" DatatypeParams="" Width="-1" Prec="-1" PrimaryKey="0" NotNull="0" AutoInc="0" IsForeignKey="0" DefaultValue="" Comments="">
<OPTIONSELECTED>
<OPTIONSELECT Value="1" />
<OPTIONSELECT Value="0" />
</OPTIONSELECTED>
</COLUMN>
</COLUMNS>
<RELATIONS_END>
<RELATION_END ID="1384" />
<RELATION_END ID="1385" />
</RELATIONS_END>
<INDICES>
<INDEX ID="1390" IndexName="PRIMARY" IndexKind="0" FKRefDef_Obj_id="-1">
<INDEXCOLUMNS>
<INDEXCOLUMN idColumn="1386" LengthParam="0" />
<INDEXCOLUMN idColumn="1388" LengthParam="0" />
</INDEXCOLUMNS>
</INDEX>
<INDEX ID="1387" IndexName="Pe\231as_has_Ordem de Seri\231o_FKIndex1" IndexKind="1" FKRefDef_Obj_id="1384">
<INDEXCOLUMNS>
<INDEXCOLUMN idColumn="1386" LengthParam="0" />
</INDEXCOLUMNS>
</INDEX>
<INDEX ID="1389" IndexName="Pe\231as_has_Ordem de Seri\231o_FKIndex2" IndexKind="1" FKRefDef_Obj_id="1385">
<INDEXCOLUMNS>
<INDEXCOLUMN idColumn="1388" LengthParam="0" />
</INDEXCOLUMNS>
</INDEX>
</INDICES>
</TABLE>
<TABLE ID="1400" Tablename="Forma de Pafamento" PrevTableName="Table_16" XPos="1313" YPos="585" TableType="0" TablePrefix="0" nmTable="0" Temporary="0" UseStandardInserts="0" StandardInserts="\n" TableOptions="DelayKeyTblUpdates=0\nPackKeys=0\nRowChecksum=0\nRowFormat=0\nUseRaid=0\nRaidType=0\n" Comments="" Collapsed="0" IsLinkedObject="0" IDLinkedModel="-1" Obj_id_Linked="-1" OrderPos="37" >
<COLUMNS>
<COLUMN ID="1405" ColName="Descri\231\227o" PrevColName="" Pos="0" idDatatype="20" DatatypeParams="" Width="-1" Prec="-1" PrimaryKey="1" NotNull="1" AutoInc="1" IsForeignKey="0" DefaultValue="" Comments="">
<OPTIONSELECTED>
<OPTIONSELECT Value="0" />
</OPTIONSELECTED>
</COLUMN>
<COLUMN ID="1407" ColName="Qauntidade M. Pascelas" PrevColName="" Pos="1" idDatatype="5" DatatypeParams="" Width="-1" Prec="-1" PrimaryKey="0" NotNull="0" AutoInc="0" IsForeignKey="0" DefaultValue="" Comments="">
<OPTIONSELECTED>
<OPTIONSELECT Value="1" />
<OPTIONSELECT Value="0" />
</OPTIONSELECTED>
</COLUMN>
<COLUMN ID="1425" ColName="Percntual de Juros" PrevColName="" Pos="1" idDatatype="5" DatatypeParams="" Width="-1" Prec="-1" PrimaryKey="0" NotNull="1" AutoInc="0" IsForeignKey="1" DefaultValue="" Comments="">
<OPTIONSELECTED>
<OPTIONSELECT Value="1" />
<OPTIONSELECT Value="0" />
</OPTIONSELECTED>
</COLUMN>
</COLUMNS>
<RELATIONS_START>
<RELATION_START ID="1439" />
</RELATIONS_START>
<RELATIONS_END>
<RELATION_END ID="1416" />
</RELATIONS_END>
<INDICES>
<INDEX ID="1406" IndexName="PRIMARY" IndexKind="0" FKRefDef_Obj_id="-1">
<INDEXCOLUMNS>
<INDEXCOLUMN idColumn="1405" LengthParam="0" />
</INDEXCOLUMNS>
</INDEX>
</INDICES>
</TABLE>
<TABLE ID="1412" Tablename="Juros" PrevTableName="Table_17" XPos="1225" YPos="294" TableType="0" TablePrefix="0" nmTable="0" Temporary="0" UseStandardInserts="0" StandardInserts="\n" TableOptions="DelayKeyTblUpdates=0\nPackKeys=0\nRowChecksum=0\nRowFormat=0\nUseRaid=0\nRaidType=0\n" Comments="" Collapsed="0" IsLinkedObject="0" IDLinkedModel="-1" Obj_id_Linked="-1" OrderPos="38" >
<COLUMNS>
<COLUMN ID="1420" ColName="Percntual de Juros" PrevColName="" Pos="1" idDatatype="5" DatatypeParams="" Width="-1" Prec="-1" PrimaryKey="1" NotNull="1" AutoInc="0" IsForeignKey="0" DefaultValue="" Comments="">
<OPTIONSELECTED>
<OPTIONSELECT Value="1" />
<OPTIONSELECT Value="0" />
</OPTIONSELECTED>
</COLUMN>
<COLUMN ID="1466" ColName="Id_Contas a Receber" PrevColName="" Pos="1" idDatatype="5" DatatypeParams="" Width="-1" Prec="-1" PrimaryKey="0" NotNull="1" AutoInc="0" IsForeignKey="1" DefaultValue="" Comments="">
<OPTIONSELECTED>
<OPTIONSELECT Value="1" />
<OPTIONSELECT Value="0" />
</OPTIONSELECTED>
</COLUMN>
</COLUMNS>
<RELATIONS_START>
<RELATION_START ID="1416" />
</RELATIONS_START>
<RELATIONS_END>
<RELATION_END ID="1465" />
</RELATIONS_END>
<INDICES>
<INDEX ID="1415" IndexName="PRIMARY" IndexKind="0" FKRefDef_Obj_id="-1">
<INDEXCOLUMNS>
<INDEXCOLUMN idColumn="1420" LengthParam="0" />
</INDEXCOLUMNS>
</INDEX>
<INDEX ID="1467" IndexName="Juros_FKIndex1" IndexKind="1" FKRefDef_Obj_id="1465">
<INDEXCOLUMNS>
<INDEXCOLUMN idColumn="1466" LengthParam="0" />
</INDEXCOLUMNS>
</INDEX>
</INDICES>
</TABLE>
<TABLE ID="1421" Tablename="Desconto" PrevTableName="Table_18" XPos="1067" YPos="488" TableType="0" TablePrefix="0" nmTable="0" Temporary="0" UseStandardInserts="0" StandardInserts="\n" TableOptions="DelayKeyTblUpdates=0\nPackKeys=0\nRowChecksum=0\nRowFormat=0\nUseRaid=0\nRaidType=0\n" Comments="" Collapsed="0" IsLinkedObject="0" IDLinkedModel="-1" Obj_id_Linked="-1" OrderPos="40" >
<COLUMNS>
<COLUMN ID="1423" ColName="Percentual de Desconto" PrevColName="" Pos="0" idDatatype="7" DatatypeParams="" Width="-1" Prec="-1" PrimaryKey="1" NotNull="1" AutoInc="1" IsForeignKey="0" DefaultValue="" Comments="">
<OPTIONSELECTED>
<OPTIONSELECT Value="0" />
</OPTIONSELECTED>
</COLUMN>
</COLUMNS>
<RELATIONS_START>
<RELATION_START ID="1429" />
<RELATION_START ID="1432" />
</RELATIONS_START>
<INDICES>
<INDEX ID="1424" IndexName="PRIMARY" IndexKind="0" FKRefDef_Obj_id="-1">
<INDEXCOLUMNS>
<INDEXCOLUMN idColumn="1423" LengthParam="0" />
</INDEXCOLUMNS>
</INDEX>
</INDICES>
</TABLE>
<TABLE ID="1442" Tablename="Contas a Receber" PrevTableName="Table_19" XPos="1180" YPos="694" TableType="0" TablePrefix="0" nmTable="0" Temporary="0" UseStandardInserts="0" StandardInserts="\n" TableOptions="DelayKeyTblUpdates=0\nPackKeys=0\nRowChecksum=0\nRowFormat=0\nUseRaid=0\nRaidType=0\n" Comments="" Collapsed="0" IsLinkedObject="0" IDLinkedModel="-1" Obj_id_Linked="-1" OrderPos="44" >
<COLUMNS>
<COLUMN ID="1463" ColName="Id_Contas a Receber" PrevColName="" Pos="6" idDatatype="5" DatatypeParams="" Width="-1" Prec="-1" PrimaryKey="1" NotNull="1" AutoInc="0" IsForeignKey="0" DefaultValue="" Comments="">
<OPTIONSELECTED>
<OPTIONSELECT Value="1" />
<OPTIONSELECT Value="0" />
</OPTIONSELECTED>
</COLUMN>
<COLUMN ID="1450" ColName="id_Ordem de Seri\231o" PrevColName="" Pos="1" idDatatype="5" DatatypeParams="" Width="-1" Prec="-1" PrimaryKey="0" NotNull="1" AutoInc="0" IsForeignKey="1" DefaultValue="" Comments="">
<OPTIONSELECTED>
<OPTIONSELECT Value="1" />
<OPTIONSELECT Value="0" />
</OPTIONSELECTED>
</COLUMN>
<COLUMN ID="1453" ColName="Data de Pagamento" PrevColName="" Pos="1" idDatatype="14" DatatypeParams="" Width="-1" Prec="-1" PrimaryKey="0" NotNull="0" AutoInc="0" IsForeignKey="0" DefaultValue="" Comments="">
<OPTIONSELECTED>
</OPTIONSELECTED>
</COLUMN>
<COLUMN ID="1454" ColName="Data de Vencimento" PrevColName="" Pos="2" idDatatype="14" DatatypeParams="" Width="-1" Prec="-1" PrimaryKey="0" NotNull="0" AutoInc="0" IsForeignKey="0" DefaultValue="" Comments="">
<OPTIONSELECTED>
</OPTIONSELECTED>
</COLUMN>
<COLUMN ID="1456" ColName="Valor Pago" PrevColName="" Pos="3" idDatatype="5" DatatypeParams="" Width="-1" Prec="-1" PrimaryKey="0" NotNull="0" AutoInc="0" IsForeignKey="0" DefaultValue="" Comments="">
<OPTIONSELECTED>
<OPTIONSELECT Value="1" />
<OPTIONSELECT Value="0" />
</OPTIONSELECTED>
</COLUMN>
<COLUMN ID="1457" ColName="Valor da Multa" PrevColName="" Pos="4" idDatatype="5" DatatypeParams="" Width="-1" Prec="-1" PrimaryKey="0" NotNull="0" AutoInc="0" IsForeignKey="0" DefaultValue="" Comments="">
<OPTIONSELECTED>
<OPTIONSELECT Value="1" />
<OPTIONSELECT Value="0" />
</OPTIONSELECTED>
</COLUMN>
</COLUMNS>
<RELATIONS_START>
<RELATION_START ID="1465" />
</RELATIONS_START>
<RELATIONS_END>
<RELATION_END ID="1449" />
</RELATIONS_END>
<INDICES>
<INDEX ID="1461" IndexName="PRIMARY" IndexKind="0" FKRefDef_Obj_id="-1">
<INDEXCOLUMNS>
<INDEXCOLUMN idColumn="1463" LengthParam="0" />
</INDEXCOLUMNS>
</INDEX>
<INDEX ID="1451" IndexName="Contas a Receber_FKIndex1" IndexKind="1" FKRefDef_Obj_id="1449">
<INDEXCOLUMNS>
<INDEXCOLUMN idColumn="1450" LengthParam="0" />
</INDEXCOLUMNS>
</INDEX>
</INDICES>
</TABLE>
</TABLES>
<RELATIONS>
<RELATION ID="1137" RelationName="Rel_02" Kind="1" SrcTable="1114" DestTable="1127" FKFields="id_Pessoa=Pessoa_id_Pessoa\n" FKFieldsComments="\n" relDirection="4" MidOffset="0" OptionalStart="0" OptionalEnd="0" CaptionOffsetX="0" CaptionOffsetY="0" StartIntervalOffsetX="0" StartIntervalOffsetY="0" EndIntervalOffsetX="0" EndIntervalOffsetY="0" CreateRefDef="1" Invisible="0" RefDef="Matching=0\nOnDelete=3\nOnUpdate=3\n" Comments="" FKRefDefIndex_Obj_id="1139" Splitted="0" IsLinkedObject="0" IDLinkedModel="-1" Obj_id_Linked="-1" OrderPos="6" />
<RELATION ID="1174" RelationName="Rel_06" Kind="1" SrcTable="1114" DestTable="1166" FKFields="id_Pessoa=id_Pessoa\n" FKFieldsComments="\n" relDirection="4" MidOffset="0" OptionalStart="0" OptionalEnd="0" CaptionOffsetX="0" CaptionOffsetY="0" StartIntervalOffsetX="0" StartIntervalOffsetY="0" EndIntervalOffsetX="0" EndIntervalOffsetY="0" CreateRefDef="1" Invisible="0" RefDef="Matching=0\nOnDelete=3\nOnUpdate=3\n" Comments="" FKRefDefIndex_Obj_id="1176" Splitted="0" IsLinkedObject="0" IDLinkedModel="-1" Obj_id_Linked="-1" OrderPos="12" />
<RELATION ID="1220" RelationName="Rel_07" Kind="2" SrcTable="1208" DestTable="1212" FKFields="id_Setor=id_Setor\n" FKFieldsComments="\n" relDirection="4" MidOffset="0" OptionalStart="0" OptionalEnd="0" CaptionOffsetX="0" CaptionOffsetY="0" StartIntervalOffsetX="0" StartIntervalOffsetY="0" EndIntervalOffsetX="0" EndIntervalOffsetY="0" CreateRefDef="1" Invisible="0" RefDef="Matching=0\nOnDelete=3\nOnUpdate=3\n" Comments="" FKRefDefIndex_Obj_id="1222" Splitted="0" IsLinkedObject="0" IDLinkedModel="-1" Obj_id_Linked="-1" OrderPos="17" />
<RELATION ID="1223" RelationName="Rel_08" Kind="2" SrcTable="1114" DestTable="1177" FKFields="id_Pessoa=id_Pessoa\n" FKFieldsComments="\n" relDirection="2" MidOffset="0" OptionalStart="0" OptionalEnd="0" CaptionOffsetX="0" CaptionOffsetY="0" StartIntervalOffsetX="0" StartIntervalOffsetY="0" EndIntervalOffsetX="0" EndIntervalOffsetY="0" CreateRefDef="1" Invisible="0" RefDef="Matching=0\nOnDelete=3\nOnUpdate=3\n" Comments="" FKRefDefIndex_Obj_id="-1" Splitted="0" IsLinkedObject="0" IDLinkedModel="-1" Obj_id_Linked="-1" OrderPos="17" />
<RELATION ID="1232" RelationName="Rel_11" Kind="2" SrcTable="1140" DestTable="1119" FKFields="id_Pessoa=id_Pessoa\n" FKFieldsComments="\n" relDirection="2" MidOffset="0" OptionalStart="0" OptionalEnd="0" CaptionOffsetX="0" CaptionOffsetY="0" StartIntervalOffsetX="0" StartIntervalOffsetY="0" EndIntervalOffsetX="0" EndIntervalOffsetY="0" CreateRefDef="1" Invisible="0" RefDef="Matching=0\nOnDelete=3\nOnUpdate=3\n" Comments="" FKRefDefIndex_Obj_id="-1" Splitted="0" IsLinkedObject="0" IDLinkedModel="-1" Obj_id_Linked="-1" OrderPos="17" />
<RELATION ID="1238" RelationName="Rel_08" Kind="2" SrcTable="1208" DestTable="1119" FKFields="id_Setor=id_Setor\n" FKFieldsComments="\n" relDirection="1" MidOffset="0" OptionalStart="0" OptionalEnd="0" CaptionOffsetX="0" CaptionOffsetY="0" StartIntervalOffsetX="0" StartIntervalOffsetY="0" EndIntervalOffsetX="0" EndIntervalOffsetY="0" CreateRefDef="1" Invisible="0" RefDef="Matching=0\nOnDelete=3\nOnUpdate=3\n" Comments="" FKRefDefIndex_Obj_id="1240" Splitted="0" IsLinkedObject="0" IDLinkedModel="-1" Obj_id_Linked="-1" OrderPos="18" />
<RELATION ID="1243" RelationName="Rel_09" Kind="2" SrcTable="1212" DestTable="1119" FKFields="id_Cargo=id_Cargo\n" FKFieldsComments="\n" relDirection="2" MidOffset="0" OptionalStart="0" OptionalEnd="0" CaptionOffsetX="0" CaptionOffsetY="0" StartIntervalOffsetX="0" StartIntervalOffsetY="0" EndIntervalOffsetX="0" EndIntervalOffsetY="0" CreateRefDef="1" Invisible="0" RefDef="Matching=0\nOnDelete=3\nOnUpdate=3\n" Comments="" FKRefDefIndex_Obj_id="1245" Splitted="0" IsLinkedObject="0" IDLinkedModel="-1" Obj_id_Linked="-1" OrderPos="19" />
<RELATION ID="1265" RelationName="Rel_12" Kind="0" SrcTable="1114" DestTable="1141" FKFields="id_Pessoa=id_Pessoa\n" FKFieldsComments="\n" relDirection="1" MidOffset="0" OptionalStart="0" OptionalEnd="0" CaptionOffsetX="0" CaptionOffsetY="0" StartIntervalOffsetX="0" StartIntervalOffsetY="0" EndIntervalOffsetX="0" EndIntervalOffsetY="0" CreateRefDef="1" Invisible="0" RefDef="Matching=0\nOnDelete=3\nOnUpdate=3\n" Comments="" FKRefDefIndex_Obj_id="1268" Splitted="0" IsLinkedObject="0" IDLinkedModel="-1" Obj_id_Linked="-1" OrderPos="19" />
<RELATION ID="1271" RelationName="Rel_13" Kind="0" SrcTable="1114" DestTable="1140" FKFields="id_Pessoa=id_Pessoa\n" FKFieldsComments="\n" relDirection="4" MidOffset="0" OptionalStart="0" OptionalEnd="0" CaptionOffsetX="0" CaptionOffsetY="0" StartIntervalOffsetX="0" StartIntervalOffsetY="0" EndIntervalOffsetX="0" EndIntervalOffsetY="0" CreateRefDef="1" Invisible="0" RefDef="Matching=0\nOnDelete=3\nOnUpdate=3\n" Comments="" FKRefDefIndex_Obj_id="1273" Splitted="0" IsLinkedObject="0" IDLinkedModel="-1" Obj_id_Linked="-1" OrderPos="19" />
<RELATION ID="1292" RelationName="Rel_14" Kind="2" SrcTable="1140" DestTable="1288" FKFields="id_Pessoa=id_Pessoa\n" FKFieldsComments="\n" relDirection="2" MidOffset="0" OptionalStart="0" OptionalEnd="0" CaptionOffsetX="0" CaptionOffsetY="0" StartIntervalOffsetX="0" StartIntervalOffsetY="0" EndIntervalOffsetX="0" EndIntervalOffsetY="0" CreateRefDef="1" Invisible="0" RefDef="Matching=0\nOnDelete=3\nOnUpdate=3\n" Comments="" FKRefDefIndex_Obj_id="1294" Splitted="0" IsLinkedObject="0" IDLinkedModel="-1" Obj_id_Linked="-1" OrderPos="21" />
<RELATION ID="1304" RelationName="Rel_17" Kind="2" SrcTable="1288" DestTable="1177" FKFields="id_Pessoa_Contato=id_Pessoa_Contato\n" FKFieldsComments="\n" relDirection="2" MidOffset="0" OptionalStart="0" OptionalEnd="0" CaptionOffsetX="0" CaptionOffsetY="0" StartIntervalOffsetX="0" StartIntervalOffsetY="0" EndIntervalOffsetX="0" EndIntervalOffsetY="0" CreateRefDef="1" Invisible="0" RefDef="Matching=0\nOnDelete=3\nOnUpdate=3\n" Comments="" FKRefDefIndex_Obj_id="1306" Splitted="0" IsLinkedObject="0" IDLinkedModel="-1" Obj_id_Linked="-1" OrderPos="22" />
<RELATION ID="1321" RelationName="Rel_18" Kind="2" SrcTable="1317" DestTable="1177" FKFields="id_Veiculos=id_Veiculos\n" FKFieldsComments="\n" relDirection="4" MidOffset="0" OptionalStart="0" OptionalEnd="0" CaptionOffsetX="0" CaptionOffsetY="0" StartIntervalOffsetX="0" StartIntervalOffsetY="0" EndIntervalOffsetX="0" EndIntervalOffsetY="0" CreateRefDef="1" Invisible="0" RefDef="Matching=0\nOnDelete=3\nOnUpdate=3\n" Comments="" FKRefDefIndex_Obj_id="1323" Splitted="0" IsLinkedObject="0" IDLinkedModel="-1" Obj_id_Linked="-1" OrderPos="24" />
<RELATION ID="1345" RelationName="Rel_19" Kind="2" SrcTable="1208" DestTable="1336" FKFields="id_Setor=id_Setor\n" FKFieldsComments="\n" relDirection="2" MidOffset="0" OptionalStart="0" OptionalEnd="0" CaptionOffsetX="0" CaptionOffsetY="0" StartIntervalOffsetX="0" StartIntervalOffsetY="0" EndIntervalOffsetX="0" EndIntervalOffsetY="0" CreateRefDef="1" Invisible="0" RefDef="Matching=0\nOnDelete=3\nOnUpdate=3\n" Comments="" FKRefDefIndex_Obj_id="1347" Splitted="0" IsLinkedObject="0" IDLinkedModel="-1" Obj_id_Linked="-1" OrderPos="26" />
<RELATION ID="1352" RelationName="Rel_20" Kind="2" SrcTable="1177" DestTable="1348" FKFields="id_Cliente=id_Cliente\n" FKFieldsComments="\n" relDirection="3" MidOffset="0" OptionalStart="0" OptionalEnd="0" CaptionOffsetX="0" CaptionOffsetY="0" StartIntervalOffsetX="0" StartIntervalOffsetY="0" EndIntervalOffsetX="0" EndIntervalOffsetY="0" CreateRefDef="1" Invisible="0" RefDef="Matching=0\nOnDelete=3\nOnUpdate=3\n" Comments="" FKRefDefIndex_Obj_id="1354" Splitted="0" IsLinkedObject="0" IDLinkedModel="-1" Obj_id_Linked="-1" OrderPos="28" />
<RELATION ID="1355" RelationName="Rel_21" Kind="2" SrcTable="1119" DestTable="1348" FKFields="id_Funcionario=id_Funcionario\n" FKFieldsComments="\n" relDirection="2" MidOffset="0" OptionalStart="0" OptionalEnd="0" CaptionOffsetX="0" CaptionOffsetY="0" StartIntervalOffsetX="0" StartIntervalOffsetY="0" EndIntervalOffsetX="0" EndIntervalOffsetY="0" CreateRefDef="1" Invisible="0" RefDef="Matching=0\nOnDelete=3\nOnUpdate=3\n" Comments="" FKRefDefIndex_Obj_id="1357" Splitted="0" IsLinkedObject="0" IDLinkedModel="-1" Obj_id_Linked="-1" OrderPos="29" />
<RELATION ID="1363" RelationName="Rel_22" Kind="2" SrcTable="1348" DestTable="1336" FKFields="id_Ordem de Seri\231o=id_Ordem de Seri\231o\n" FKFieldsComments="\n" relDirection="1" MidOffset="0" OptionalStart="0" OptionalEnd="0" CaptionOffsetX="0" CaptionOffsetY="0" StartIntervalOffsetX="0" StartIntervalOffsetY="0" EndIntervalOffsetX="0" EndIntervalOffsetY="0" CreateRefDef="1" Invisible="0" RefDef="Matching=0\nOnDelete=3\nOnUpdate=3\n" Comments="" FKRefDefIndex_Obj_id="1365" Splitted="0" IsLinkedObject="0" IDLinkedModel="-1" Obj_id_Linked="-1" OrderPos="30" />
<RELATION ID="1366" RelationName="Rel_23" Kind="2" SrcTable="1119" DestTable="1348" FKFields="id_Funcionario=id_Funcionario\n" FKFieldsComments="\n" relDirection="2" MidOffset="0" OptionalStart="0" OptionalEnd="0" CaptionOffsetX="0" CaptionOffsetY="0" StartIntervalOffsetX="0" StartIntervalOffsetY="0" EndIntervalOffsetX="0" EndIntervalOffsetY="0" CreateRefDef="1" Invisible="0" RefDef="Matching=0\nOnDelete=3\nOnUpdate=3\n" Comments="" FKRefDefIndex_Obj_id="1367" Splitted="0" IsLinkedObject="0" IDLinkedModel="-1" Obj_id_Linked="-1" OrderPos="31" />
<RELATION ID="1376" RelationName="Rel_24" Kind="2" SrcTable="1119" DestTable="1336" FKFields="id_Funcionario=id_Funcionario\n" FKFieldsComments="\n" relDirection="2" MidOffset="0" OptionalStart="0" OptionalEnd="0" CaptionOffsetX="0" CaptionOffsetY="0" StartIntervalOffsetX="0" StartIntervalOffsetY="0" EndIntervalOffsetX="0" EndIntervalOffsetY="0" CreateRefDef="1" Invisible="0" RefDef="Matching=0\nOnDelete=3\nOnUpdate=3\n" Comments="" FKRefDefIndex_Obj_id="1378" Splitted="0" IsLinkedObject="0" IDLinkedModel="-1" Obj_id_Linked="-1" OrderPos="32" />
<RELATION ID="1384" RelationName="Rel_25" Kind="1" SrcTable="1379" DestTable="1383" FKFields="id_Pe\231as=id_Pe\231as\n" FKFieldsComments="\n" relDirection="4" MidOffset="0" OptionalStart="0" OptionalEnd="0" CaptionOffsetX="0" CaptionOffsetY="0" StartIntervalOffsetX="0" StartIntervalOffsetY="0" EndIntervalOffsetX="0" EndIntervalOffsetY="0" CreateRefDef="1" Invisible="0" RefDef="Matching=0\nOnDelete=3\nOnUpdate=3\n" Comments="" FKRefDefIndex_Obj_id="1387" Splitted="0" IsLinkedObject="0" IDLinkedModel="-1" Obj_id_Linked="-1" OrderPos="35" />
<RELATION ID="1385" RelationName="Rel_26" Kind="1" SrcTable="1348" DestTable="1383" FKFields="id_Ordem de Seri\231o=id_Ordem de Seri\231o\n" FKFieldsComments="\n" relDirection="4" MidOffset="0" OptionalStart="0" OptionalEnd="0" CaptionOffsetX="0" CaptionOffsetY="0" StartIntervalOffsetX="0" StartIntervalOffsetY="0" EndIntervalOffsetX="0" EndIntervalOffsetY="0" CreateRefDef="1" Invisible="0" RefDef="Matching=0\nOnDelete=3\nOnUpdate=3\n" Comments="" FKRefDefIndex_Obj_id="1389" Splitted="0" IsLinkedObject="0" IDLinkedModel="-1" Obj_id_Linked="-1" OrderPos="36" />
<RELATION ID="1416" RelationName="Rel_27" Kind="2" SrcTable="1412" DestTable="1400" FKFields="Percntual de Juros=Percntual de Juros\n" FKFieldsComments="\n" relDirection="3" MidOffset="0" OptionalStart="0" OptionalEnd="0" CaptionOffsetX="0" CaptionOffsetY="0" StartIntervalOffsetX="0" StartIntervalOffsetY="0" EndIntervalOffsetX="0" EndIntervalOffsetY="0" CreateRefDef="1" Invisible="0" RefDef="Matching=0\nOnDelete=3\nOnUpdate=3\n" Comments="" FKRefDefIndex_Obj_id="-1" Splitted="0" IsLinkedObject="0" IDLinkedModel="-1" Obj_id_Linked="-1" OrderPos="39" />
<RELATION ID="1429" RelationName="Rel_29" Kind="2" SrcTable="1421" DestTable="1336" FKFields="Percentual de Desconto=Percentual de Desconto\n" FKFieldsComments="\n" relDirection="1" MidOffset="0" OptionalStart="0" OptionalEnd="0" CaptionOffsetX="0" CaptionOffsetY="0" StartIntervalOffsetX="0" StartIntervalOffsetY="0" EndIntervalOffsetX="0" EndIntervalOffsetY="0" CreateRefDef="1" Invisible="0" RefDef="Matching=0\nOnDelete=3\nOnUpdate=3\n" Comments="" FKRefDefIndex_Obj_id="1431" Splitted="0" IsLinkedObject="0" IDLinkedModel="-1" Obj_id_Linked="-1" OrderPos="41" />
<RELATION ID="1432" RelationName="Rel_30" Kind="2" SrcTable="1421" DestTable="1379" FKFields="Percentual de Desconto=Percentual de Desconto\n" FKFieldsComments="\n" relDirection="3" MidOffset="0" OptionalStart="0" OptionalEnd="0" CaptionOffsetX="0" CaptionOffsetY="0" StartIntervalOffsetX="0" StartIntervalOffsetY="0" EndIntervalOffsetX="0" EndIntervalOffsetY="0" CreateRefDef="1" Invisible="0" RefDef="Matching=0\nOnDelete=3\nOnUpdate=3\n" Comments="" FKRefDefIndex_Obj_id="1434" Splitted="0" IsLinkedObject="0" IDLinkedModel="-1" Obj_id_Linked="-1" OrderPos="42" />
<RELATION ID="1439" RelationName="Rel_32" Kind="2" SrcTable="1400" DestTable="1348" FKFields="Descri\231\227o=Descri\231\227o\n" FKFieldsComments="\n" relDirection="4" MidOffset="0" OptionalStart="0" OptionalEnd="0" CaptionOffsetX="0" CaptionOffsetY="0" StartIntervalOffsetX="0" StartIntervalOffsetY="0" EndIntervalOffsetX="0" EndIntervalOffsetY="0" CreateRefDef="1" Invisible="0" RefDef="Matching=0\nOnDelete=3\nOnUpdate=3\n" Comments="" FKRefDefIndex_Obj_id="1441" Splitted="0" IsLinkedObject="0" IDLinkedModel="-1" Obj_id_Linked="-1" OrderPos="43" />
<RELATION ID="1449" RelationName="Rel_34" Kind="2" SrcTable="1348" DestTable="1442" FKFields="id_Ordem de Seri\231o=id_Ordem de Seri\231o\n" FKFieldsComments="\n" relDirection="2" MidOffset="0" OptionalStart="0" OptionalEnd="0" CaptionOffsetX="0" CaptionOffsetY="0" StartIntervalOffsetX="0" StartIntervalOffsetY="0" EndIntervalOffsetX="0" EndIntervalOffsetY="0" CreateRefDef="1" Invisible="0" RefDef="Matching=0\nOnDelete=3\nOnUpdate=3\n" Comments="" FKRefDefIndex_Obj_id="1451" Splitted="0" IsLinkedObject="0" IDLinkedModel="-1" Obj_id_Linked="-1" OrderPos="45" />
<RELATION ID="1465" RelationName="Rel_36" Kind="2" SrcTable="1442" DestTable="1412" FKFields="Id_Contas a Receber=Id_Contas a Receber\n" FKFieldsComments="\n" relDirection="1" MidOffset="0" OptionalStart="0" OptionalEnd="0" CaptionOffsetX="0" CaptionOffsetY="0" StartIntervalOffsetX="0" StartIntervalOffsetY="0" EndIntervalOffsetX="0" EndIntervalOffsetY="0" CreateRefDef="1" Invisible="0" RefDef="Matching=0\nOnDelete=3\nOnUpdate=3\n" Comments="" FKRefDefIndex_Obj_id="1467" Splitted="0" IsLinkedObject="0" IDLinkedModel="-1" Obj_id_Linked="-1" OrderPos="46" />
</RELATIONS>
<NOTES>
</NOTES>
<IMAGES>
</IMAGES>
</METADATA>
<PLUGINDATA>
<PLUGINDATARECORDS>
</PLUGINDATARECORDS>
</PLUGINDATA>
<QUERYDATA>
<QUERYRECORDS>
</QUERYRECORDS>
</QUERYDATA>
<LINKEDMODELS>
</LINKEDMODELS>
</DBMODEL>
